{
  "last_updated": "2026-05-12 21:30:04 UTC",
  "mode": "paper",
  "summary": {
    "total_pnl": -28.155,
    "total_pnl_slip": -35.197,
    "markets_traded": 41,
    "wins": 69,
    "losses": 83,
    "win_rate": 45.4,
    "P1L_pnl": -7.046,
    "P2A_pnl": -2.202,
    "DRIFT_pnl": 7.033,
    "FADE_pnl": -21.371,
    "SQUEEZE_pnl": -3.722,
    "ANCHOR_pnl": -0.847,
    "P1L_pnl_slip": -8.59,
    "P2A_pnl_slip": -2.409,
    "DRIFT_pnl_slip": 4.558,
    "FADE_pnl_slip": -22.74,
    "SQUEEZE_pnl_slip": -4.739,
    "ANCHOR_pnl_slip": -1.277,
    "P1L_wins": 12,
    "P2A_wins": 5,
    "DRIFT_wins": 26,
    "FADE_wins": 7,
    "SQUEEZE_wins": 13,
    "ANCHOR_wins": 6,
    "P1L_losses": 20,
    "P2A_losses": 3,
    "DRIFT_losses": 13,
    "FADE_losses": 32,
    "SQUEEZE_losses": 11,
    "ANCHOR_losses": 4
  },
  "trades": [
    {
      "market": 258,
      "strategy": "ANCHOR",
      "side": "DOWN",
      "entry": 0.63,
      "result": "loss",
      "net_pnl": -1.02,
      "slip_pnl": -1.02,
      "winner": "UP",
      "mode": "paper"
    },
    {
      "market": 258,
      "strategy": "SQUEEZE",
      "side": "UP",
      "entry": 0.4,
      "result": "win",
      "net_pnl": 1.48,
      "slip_pnl": 1.3056,
      "winner": "UP",
      "mode": "paper"
    },
    {
      "market": 258,
      "strategy": "P1L",
      "side": "UP",
      "entry": 0.44,
      "result": "loss",
      "net_pnl": -1.02,
      "slip_pnl": -1.02,
      "winner": "DOWN",
      "mode": "paper"
    },
    {
      "market": 258,
      "strategy": "DRIFT",
      "side": "UP",
      "entry": 0.5,
      "result": "loss",
      "net_pnl": -1.02,
      "slip_pnl": -1.02,
      "winner": "DOWN",
      "mode": "paper"
    },
    {
      "market": 258,
      "strategy": "SQUEEZE",
      "side": "UP",
      "entry": 0.57,
      "result": "loss",
      "net_pnl": -1.02,
      "slip_pnl": -1.02,
      "winner": "DOWN",
      "mode": "paper"
    },
    {
      "market": 258,
      "strategy": "FADE",
      "side": "DOWN",
      "entry": 0.42,
      "result": "win",
      "net_pnl": 1.361,
      "slip_pnl": 1.2022,
      "winner": "DOWN",
      "mode": "paper"
    },
    {
      "market": 258,
      "strategy": "P1L",
      "side": "UP",
      "entry": 0.485,
      "result": "win",
      "net_pnl": 1.0419,
      "slip_pnl": 0.9217,
      "winner": "UP",
      "mode": "paper"
    },
    {
      "market": 258,
      "strategy": "DRIFT",
      "side": "UP",
      "entry": 0.54,
      "result": "win",
      "net_pnl": 0.8319,
      "slip_pnl": 0.7344,
      "winner": "UP",
      "mode": "paper"
    },
    {
      "market": 258,
      "strategy": "FADE",
      "side": "DOWN",
      "entry": 0.38,
      "result": "loss",
      "net_pnl": -1.02,
      "slip_pnl": -1.02,
      "winner": "UP",
      "mode": "paper"
    },
    {
      "market": 258,
      "strategy": "SQUEEZE",
      "side": "UP",
      "entry": 0.88,
      "result": "win",
      "net_pnl": 0.1164,
      "slip_pnl": 0.0789,
      "winner": "UP",
      "mode": "paper"
    },
    {
      "market": 258,
      "strategy": "DRIFT",
      "side": "UP",
      "entry": 0.66,
      "result": "loss",
      "net_pnl": -1.02,
      "slip_pnl": -1.02,
      "winner": "DOWN",
      "mode": "paper"
    },
    {
      "market": 258,
      "strategy": "SQUEEZE",
      "side": "DOWN",
      "entry": 0.45,
      "result": "win",
      "net_pnl": 1.2022,
      "slip_pnl": 1.0633,
      "winner": "DOWN",
      "mode": "paper"
    },
    {
      "market": 258,
      "strategy": "FADE",
      "side": "UP",
      "entry": 0.43,
      "result": "loss",
      "net_pnl": -1.02,
      "slip_pnl": -1.02,
      "winner": "DOWN",
      "mode": "paper"
    },
    {
      "market": 258,
      "strategy": "P2A",
      "side": "UP",
      "entry": 0.72,
      "result": "loss",
      "net_pnl": -1.02,
      "slip_pnl": -1.02,
      "winner": "DOWN",
      "mode": "paper"
    },
    {
      "market": 258,
      "strategy": "DRIFT",
      "side": "UP",
      "entry": 0.68,
      "result": "win",
      "net_pnl": 0.4506,
      "slip_pnl": 0.3885,
      "winner": "UP",
      "mode": "paper"
    },
    {
      "market": 258,
      "strategy": "FADE",
      "side": "DOWN",
      "entry": 0.2,
      "result": "loss",
      "net_pnl": -1.02,
      "slip_pnl": -1.02,
      "winner": "UP",
      "mode": "paper"
    },
    {
      "market": 258,
      "strategy": "SQUEEZE",
      "side": "UP",
      "entry": 0.8,
      "result": "win",
      "net_pnl": 0.23,
      "slip_pnl": 0.1848,
      "winner": "UP",
      "mode": "paper"
    },
    {
      "market": 258,
      "strategy": "P2A",
      "side": "UP",
      "entry": 0.89,
      "result": "win",
      "net_pnl": 0.1036,
      "slip_pnl": 0.067,
      "winner": "UP",
      "mode": "paper"
    },
    {
      "market": 258,
      "strategy": "DRIFT",
      "side": "DOWN",
      "entry": 0.5,
      "result": "loss",
      "net_pnl": -1.02,
      "slip_pnl": -1.02,
      "winner": "UP",
      "mode": "paper"
    },
    {
      "market": 258,
      "strategy": "SQUEEZE",
      "side": "DOWN",
      "entry": 0.52,
      "result": "loss",
      "net_pnl": -1.02,
      "slip_pnl": -1.02,
      "winner": "UP",
      "mode": "paper"
    },
    {
      "market": 258,
      "strategy": "FADE",
      "side": "DOWN",
      "entry": 0.19,
      "result": "loss",
      "net_pnl": -1.02,
      "slip_pnl": -1.02,
      "winner": "UP",
      "mode": "paper"
    },
    {
      "market": 258,
      "strategy": "P1L",
      "side": "UP",
      "entry": 0.475,
      "result": "loss",
      "net_pnl": -1.02,
      "slip_pnl": -1.02,
      "winner": "DOWN",
      "mode": "paper"
    },
    {
      "market": 258,
      "strategy": "DRIFT",
      "side": "UP",
      "entry": 0.53,
      "result": "loss",
      "net_pnl": -1.02,
      "slip_pnl": -1.02,
      "winner": "DOWN",
      "mode": "paper"
    },
    {
      "market": 258,
      "strategy": "FADE",
      "side": "UP",
      "entry": 0.35,
      "result": "loss",
      "net_pnl": -1.02,
      "slip_pnl": -1.02,
      "winner": "DOWN",
      "mode": "paper"
    },
    {
      "market": 258,
      "strategy": "ANCHOR",
      "side": "DOWN",
      "entry": 0.57,
      "result": "win",
      "net_pnl": 0.7344,
      "slip_pnl": 0.6467,
      "winner": "DOWN",
      "mode": "paper"
    },
    {
      "market": 258,
      "strategy": "P1L",
      "side": "UP",
      "entry": 0.455,
      "result": "loss",
      "net_pnl": -1.02,
      "slip_pnl": -1.02,
      "winner": "DOWN",
      "mode": "paper"
    },
    {
      "market": 258,
      "strategy": "DRIFT",
      "side": "DOWN",
      "entry": 0.48,
      "result": "win",
      "net_pnl": 1.0633,
      "slip_pnl": 0.9408,
      "winner": "DOWN",
      "mode": "paper"
    },
    {
      "market": 258,
      "strategy": "FADE",
      "side": "UP",
      "entry": 0.33,
      "result": "loss",
      "net_pnl": -1.02,
      "slip_pnl": -1.02,
      "winner": "DOWN",
      "mode": "paper"
    },
    {
      "market": 258,
      "strategy": "P2A",
      "side": "UP",
      "entry": 0.85,
      "result": "loss",
      "net_pnl": -1.02,
      "slip_pnl": -1.02,
      "winner": "DOWN",
      "mode": "paper"
    },
    {
      "market": 258,
      "strategy": "P1L",
      "side": "UP",
      "entry": 0.485,
      "result": "loss",
      "net_pnl": -1.02,
      "slip_pnl": -1.02,
      "winner": "DOWN",
      "mode": "paper"
    },
    {
      "market": 258,
      "strategy": "DRIFT",
      "side": "UP",
      "entry": 0.42,
      "result": "pending",
      "net_pnl": null,
      "slip_pnl": null,
      "winner": "",
      "mode": "paper"
    },
    {
      "market": 258,
      "strategy": "SQUEEZE",
      "side": "DOWN",
      "entry": 0.62,
      "result": "pending",
      "net_pnl": null,
      "slip_pnl": null,
      "winner": "",
      "mode": "paper"
    },
    {
      "market": 258,
      "strategy": "FADE",
      "side": "UP",
      "entry": 0.36,
      "result": "pending",
      "net_pnl": null,
      "slip_pnl": null,
      "winner": "",
      "mode": "paper"
    },
    {
      "market": 258,
      "strategy": "ANCHOR",
      "side": "DOWN",
      "entry": 0.66,
      "result": "pending",
      "net_pnl": null,
      "slip_pnl": null,
      "winner": "",
      "mode": "paper"
    },
    {
      "market": 258,
      "strategy": "P1L",
      "side": "UP",
      "entry": 0.445,
      "result": "pending",
      "net_pnl": null,
      "slip_pnl": null,
      "winner": "",
      "mode": "paper"
    },
    {
      "market": 258,
      "strategy": "DRIFT",
      "side": "DOWN",
      "entry": 0.65,
      "result": "pending",
      "net_pnl": null,
      "slip_pnl": null,
      "winner": "",
      "mode": "paper"
    },
    {
      "market": 258,
      "strategy": "FADE",
      "side": "UP",
      "entry": 0.29,
      "result": "pending",
      "net_pnl": null,
      "slip_pnl": null,
      "winner": "",
      "mode": "paper"
    }
  ]
}