{
  "last_updated": "2026-05-12 20:35:22 UTC",
  "mode": "paper",
  "summary": {
    "total_pnl": -19.374,
    "total_pnl_slip": -24.606,
    "markets_traded": 30,
    "wins": 51,
    "losses": 60,
    "win_rate": 45.9,
    "P1L_pnl": -4.988,
    "P2A_pnl": -0.265,
    "DRIFT_pnl": 8.265,
    "FADE_pnl": -16.116,
    "SQUEEZE_pnl": -5.14,
    "ANCHOR_pnl": -1.129,
    "P1L_pnl_slip": -6.181,
    "P2A_pnl_slip": -0.436,
    "DRIFT_pnl_slip": 6.254,
    "FADE_pnl_slip": -17.143,
    "SQUEEZE_pnl_slip": -5.701,
    "ANCHOR_pnl_slip": -1.399,
    "P1L_wins": 9,
    "P2A_wins": 4,
    "DRIFT_wins": 21,
    "FADE_wins": 5,
    "SQUEEZE_wins": 8,
    "ANCHOR_wins": 4,
    "P1L_losses": 15,
    "P2A_losses": 1,
    "DRIFT_losses": 8,
    "FADE_losses": 24,
    "SQUEEZE_losses": 9,
    "ANCHOR_losses": 3
  },
  "trades": [
    {
      "market": 248,
      "strategy": "DRIFT",
      "side": "DOWN",
      "entry": 0.49,
      "result": "loss",
      "net_pnl": -1.02,
      "slip_pnl": -1.02,
      "winner": "UP",
      "mode": "paper"
    },
    {
      "market": 248,
      "strategy": "SQUEEZE",
      "side": "DOWN",
      "entry": 0.53,
      "result": "loss",
      "net_pnl": -1.02,
      "slip_pnl": -1.02,
      "winner": "UP",
      "mode": "paper"
    },
    {
      "market": 248,
      "strategy": "FADE",
      "side": "UP",
      "entry": 0.45,
      "result": "win",
      "net_pnl": 1.2022,
      "slip_pnl": 1.0633,
      "winner": "UP",
      "mode": "paper"
    },
    {
      "market": 248,
      "strategy": "P2A",
      "side": "UP",
      "entry": 0.73,
      "result": "win",
      "net_pnl": 0.3499,
      "slip_pnl": 0.2958,
      "winner": "UP",
      "mode": "paper"
    },
    {
      "market": 248,
      "strategy": "P1L",
      "side": "DOWN",
      "entry": 0.415,
      "result": "loss",
      "net_pnl": -1.02,
      "slip_pnl": -1.02,
      "winner": "UP",
      "mode": "paper"
    },
    {
      "market": 248,
      "strategy": "DRIFT",
      "side": "UP",
      "entry": 0.45,
      "result": "win",
      "net_pnl": 1.2022,
      "slip_pnl": 1.0633,
      "winner": "UP",
      "mode": "paper"
    },
    {
      "market": 248,
      "strategy": "FADE",
      "side": "DOWN",
      "entry": 0.31,
      "result": "loss",
      "net_pnl": -1.02,
      "slip_pnl": -1.02,
      "winner": "UP",
      "mode": "paper"
    },
    {
      "market": 248,
      "strategy": "SQUEEZE",
      "side": "DOWN",
      "entry": 0.73,
      "result": "loss",
      "net_pnl": -1.02,
      "slip_pnl": -1.02,
      "winner": "UP",
      "mode": "paper"
    },
    {
      "market": 248,
      "strategy": "P2A",
      "side": "UP",
      "entry": 0.88,
      "result": "win",
      "net_pnl": 0.1164,
      "slip_pnl": 0.0789,
      "winner": "UP",
      "mode": "paper"
    },
    {
      "market": 248,
      "strategy": "P1L",
      "side": "UP",
      "entry": 0.435,
      "result": "loss",
      "net_pnl": -1.02,
      "slip_pnl": -1.02,
      "winner": "DOWN",
      "mode": "paper"
    },
    {
      "market": 248,
      "strategy": "DRIFT",
      "side": "DOWN",
      "entry": 0.68,
      "result": "win",
      "net_pnl": 0.4506,
      "slip_pnl": 0.3885,
      "winner": "DOWN",
      "mode": "paper"
    },
    {
      "market": 248,
      "strategy": "FADE",
      "side": "UP",
      "entry": 0.17,
      "result": "loss",
      "net_pnl": -1.02,
      "slip_pnl": -1.02,
      "winner": "DOWN",
      "mode": "paper"
    },
    {
      "market": 248,
      "strategy": "P1L",
      "side": "UP",
      "entry": 0.485,
      "result": "loss",
      "net_pnl": -1.02,
      "slip_pnl": -1.02,
      "winner": "DOWN",
      "mode": "paper"
    },
    {
      "market": 248,
      "strategy": "DRIFT",
      "side": "UP",
      "entry": 0.43,
      "result": "loss",
      "net_pnl": -1.02,
      "slip_pnl": -1.02,
      "winner": "DOWN",
      "mode": "paper"
    },
    {
      "market": 248,
      "strategy": "FADE",
      "side": "UP",
      "entry": 0.22,
      "result": "loss",
      "net_pnl": -1.02,
      "slip_pnl": -1.02,
      "winner": "DOWN",
      "mode": "paper"
    },
    {
      "market": 248,
      "strategy": "ANCHOR",
      "side": "DOWN",
      "entry": 0.87,
      "result": "win",
      "net_pnl": 0.1294,
      "slip_pnl": 0.0911,
      "winner": "DOWN",
      "mode": "paper"
    },
    {
      "market": 248,
      "strategy": "P1L",
      "side": "DOWN",
      "entry": 0.485,
      "result": "loss",
      "net_pnl": -1.02,
      "slip_pnl": -1.02,
      "winner": "UP",
      "mode": "paper"
    },
    {
      "market": 248,
      "strategy": "DRIFT",
      "side": "UP",
      "entry": 0.64,
      "result": "win",
      "net_pnl": 0.5425,
      "slip_pnl": 0.4725,
      "winner": "UP",
      "mode": "paper"
    },
    {
      "market": 248,
      "strategy": "SQUEEZE",
      "side": "UP",
      "entry": 0.71,
      "result": "win",
      "net_pnl": 0.3885,
      "slip_pnl": 0.3314,
      "winner": "UP",
      "mode": "paper"
    },
    {
      "market": 248,
      "strategy": "FADE",
      "side": "DOWN",
      "entry": 0.35,
      "result": "loss",
      "net_pnl": -1.02,
      "slip_pnl": -1.02,
      "winner": "UP",
      "mode": "paper"
    },
    {
      "market": 248,
      "strategy": "ANCHOR",
      "side": "DOWN",
      "entry": 0.49,
      "result": "loss",
      "net_pnl": -1.02,
      "slip_pnl": -1.02,
      "winner": "UP",
      "mode": "paper"
    },
    {
      "market": 248,
      "strategy": "P1L",
      "side": "DOWN",
      "entry": 0.495,
      "result": "win",
      "net_pnl": 1.0002,
      "slip_pnl": 0.8848,
      "winner": "DOWN",
      "mode": "paper"
    },
    {
      "market": 248,
      "strategy": "DRIFT",
      "side": "DOWN",
      "entry": 0.54,
      "result": "win",
      "net_pnl": 0.8319,
      "slip_pnl": 0.7344,
      "winner": "DOWN",
      "mode": "paper"
    },
    {
      "market": 248,
      "strategy": "FADE",
      "side": "UP",
      "entry": 0.28,
      "result": "loss",
      "net_pnl": -1.02,
      "slip_pnl": -1.02,
      "winner": "DOWN",
      "mode": "paper"
    },
    {
      "market": 248,
      "strategy": "P2A",
      "side": "UP",
      "entry": 0.91,
      "result": "loss",
      "net_pnl": -1.02,
      "slip_pnl": -1.02,
      "winner": "DOWN",
      "mode": "paper"
    },
    {
      "market": 248,
      "strategy": "P1L",
      "side": "UP",
      "entry": 0.485,
      "result": "win",
      "net_pnl": 1.0419,
      "slip_pnl": 0.9217,
      "winner": "UP",
      "mode": "paper"
    },
    {
      "market": 248,
      "strategy": "DRIFT",
      "side": "UP",
      "entry": 0.7,
      "result": "win",
      "net_pnl": 0.4086,
      "slip_pnl": 0.3499,
      "winner": "UP",
      "mode": "paper"
    },
    {
      "market": 248,
      "strategy": "SQUEEZE",
      "side": "UP",
      "entry": 0.73,
      "result": "win",
      "net_pnl": 0.3499,
      "slip_pnl": 0.2958,
      "winner": "UP",
      "mode": "paper"
    },
    {
      "market": 248,
      "strategy": "FADE",
      "side": "DOWN",
      "entry": 0.26,
      "result": "loss",
      "net_pnl": -1.02,
      "slip_pnl": -1.02,
      "winner": "UP",
      "mode": "paper"
    },
    {
      "market": 248,
      "strategy": "ANCHOR",
      "side": "UP",
      "entry": 0.6,
      "result": "win",
      "net_pnl": 0.6467,
      "slip_pnl": 0.5673,
      "winner": "UP",
      "mode": "paper"
    },
    {
      "market": 248,
      "strategy": "P1L",
      "side": "DOWN",
      "entry": 0.495,
      "result": "pending",
      "net_pnl": null,
      "slip_pnl": null,
      "winner": "",
      "mode": "paper"
    },
    {
      "market": 248,
      "strategy": "SQUEEZE",
      "side": "DOWN",
      "entry": 0.69,
      "result": "pending",
      "net_pnl": null,
      "slip_pnl": null,
      "winner": "",
      "mode": "paper"
    },
    {
      "market": 248,
      "strategy": "DRIFT",
      "side": "UP",
      "entry": 0.32,
      "result": "pending",
      "net_pnl": null,
      "slip_pnl": null,
      "winner": "",
      "mode": "paper"
    },
    {
      "market": 248,
      "strategy": "FADE",
      "side": "UP",
      "entry": 0.35,
      "result": "pending",
      "net_pnl": null,
      "slip_pnl": null,
      "winner": "",
      "mode": "paper"
    },
    {
      "market": 248,
      "strategy": "P1L",
      "side": "DOWN",
      "entry": 0.495,
      "result": "pending",
      "net_pnl": null,
      "slip_pnl": null,
      "winner": "",
      "mode": "paper"
    }
  ]
}