{
  "last_updated": "2026-07-10 01:22:40 UTC",
  "mode": "paper",
  "summary": {
    "total_pnl": 1476.597,
    "total_pnl_slip": -1826.838,
    "markets_traded": 11283,
    "wins": 9382,
    "losses": 8620,
    "win_rate": 52.1,
    "TIGHT_pnl": 425.362,
    "HOUR_pnl": 268.708,
    "SECOND_pnl": 252.085,
    "P2A_pnl": 5.325,
    "HOUR_REFINED_pnl": 150.74,
    "CHEAP_FLOOR_pnl": 102.794,
    "SECOND_TIERED_pnl": 73.639,
    "CONSENSUS_3_pnl": 96.455,
    "EARLY_TIMING_pnl": 30.511,
    "TIGHT_pnl_slip": -418.627,
    "HOUR_pnl_slip": 66.867,
    "SECOND_pnl_slip": -91.436,
    "P2A_pnl_slip": -140.313,
    "HOUR_REFINED_pnl_slip": 18.654,
    "CHEAP_FLOOR_pnl_slip": -4.082,
    "SECOND_TIERED_pnl_slip": -73.305,
    "CONSENSUS_3_pnl_slip": 1.035,
    "EARLY_TIMING_pnl_slip": -53.107,
    "TIGHT_wins": 2480,
    "HOUR_wins": 733,
    "SECOND_wins": 1414,
    "P2A_wins": 2952,
    "HOUR_REFINED_wins": 656,
    "CHEAP_FLOOR_wins": 87,
    "SECOND_TIERED_wins": 100,
    "CONSENSUS_3_wins": 564,
    "EARLY_TIMING_wins": 396,
    "TIGHT_losses": 3420,
    "HOUR_losses": 775,
    "SECOND_losses": 1402,
    "P2A_losses": 776,
    "HOUR_REFINED_losses": 550,
    "CHEAP_FLOOR_losses": 403,
    "SECOND_TIERED_losses": 555,
    "CONSENSUS_3_losses": 360,
    "EARLY_TIMING_losses": 379
  },
  "trades": [
    {
      "market": 17,
      "slug": "btc-updown-5m-1783642200",
      "strategy": "HOUR_REFINED",
      "side": "DOWN",
      "entry": 0.84,
      "elapsed": 60,
      "result": "loss",
      "net_pnl": -1.02,
      "slip_pnl": -1.02,
      "winner": "UP",
      "mode": "paper",
      "time": "2026-07-10 01:22:40 UTC"
    },
    {
      "market": 17,
      "slug": "btc-updown-5m-1783642200",
      "strategy": "TIGHT",
      "side": "DOWN",
      "entry": 0.84,
      "elapsed": 60,
      "result": "loss",
      "net_pnl": -1.02,
      "slip_pnl": -1.02,
      "winner": "UP",
      "mode": "paper",
      "time": "2026-07-10 01:22:40 UTC"
    },
    {
      "market": 17,
      "slug": "btc-updown-5m-1783642200",
      "strategy": "CONSENSUS_3",
      "side": "DOWN",
      "entry": 0.79,
      "elapsed": 65,
      "result": "loss",
      "net_pnl": -1.02,
      "slip_pnl": -1.02,
      "winner": "UP",
      "mode": "paper",
      "time": "2026-07-10 01:22:40 UTC"
    },
    {
      "market": 17,
      "slug": "btc-updown-5m-1783642200",
      "strategy": "EARLY_TIMING",
      "side": "DOWN",
      "entry": 0.82,
      "elapsed": 80,
      "result": "loss",
      "net_pnl": -1.02,
      "slip_pnl": -1.02,
      "winner": "UP",
      "mode": "paper",
      "time": "2026-07-10 01:22:40 UTC"
    },
    {
      "market": 17,
      "slug": "btc-updown-5m-1783642200",
      "strategy": "SECOND",
      "side": "DOWN",
      "entry": 0.84,
      "elapsed": 90,
      "result": "loss",
      "net_pnl": -1.02,
      "slip_pnl": -1.02,
      "winner": "UP",
      "mode": "paper",
      "time": "2026-07-10 01:22:40 UTC"
    },
    {
      "market": 17,
      "slug": "btc-updown-5m-1783642200",
      "strategy": "P2A",
      "side": "UP",
      "entry": 0.91,
      "elapsed": 292,
      "result": "win",
      "net_pnl": 0.0789,
      "slip_pnl": 0.0438,
      "winner": "UP",
      "mode": "paper",
      "time": "2026-07-10 01:22:40 UTC"
    },
    {
      "market": 17,
      "slug": "btc-updown-5m-1783642500",
      "strategy": "P2A",
      "side": "DOWN",
      "entry": 0.67,
      "elapsed": 276,
      "result": "win",
      "net_pnl": 0.4725,
      "slip_pnl": 0.4086,
      "winner": "DOWN",
      "mode": "paper",
      "time": "2026-07-10 01:22:40 UTC"
    },
    {
      "market": 17,
      "slug": "btc-updown-5m-1783642800",
      "strategy": "TIGHT",
      "side": "UP",
      "entry": 0.7,
      "elapsed": 105,
      "result": "loss",
      "net_pnl": -1.02,
      "slip_pnl": -1.02,
      "winner": "DOWN",
      "mode": "paper",
      "time": "2026-07-10 01:22:40 UTC"
    },
    {
      "market": 17,
      "slug": "btc-updown-5m-1783642800",
      "strategy": "SECOND",
      "side": "UP",
      "entry": 0.71,
      "elapsed": 105,
      "result": "loss",
      "net_pnl": -1.02,
      "slip_pnl": -1.02,
      "winner": "DOWN",
      "mode": "paper",
      "time": "2026-07-10 01:22:40 UTC"
    },
    {
      "market": 17,
      "slug": "btc-updown-5m-1783643100",
      "strategy": "P2A",
      "side": "DOWN",
      "entry": 0.62,
      "elapsed": 261,
      "result": "loss",
      "net_pnl": -1.02,
      "slip_pnl": -1.02,
      "winner": "UP",
      "mode": "paper",
      "time": "2026-07-10 01:22:40 UTC"
    },
    {
      "market": 17,
      "slug": "btc-updown-5m-1783643700",
      "strategy": "TIGHT",
      "side": "UP",
      "entry": 0.72,
      "elapsed": 75,
      "result": "win",
      "net_pnl": 0.3689,
      "slip_pnl": 0.3133,
      "winner": "UP",
      "mode": "paper",
      "time": "2026-07-10 01:22:40 UTC"
    },
    {
      "market": 17,
      "slug": "btc-updown-5m-1783643700",
      "strategy": "HOUR_REFINED",
      "side": "UP",
      "entry": 0.72,
      "elapsed": 75,
      "result": "win",
      "net_pnl": 0.3689,
      "slip_pnl": 0.3133,
      "winner": "UP",
      "mode": "paper",
      "time": "2026-07-10 01:22:40 UTC"
    },
    {
      "market": 17,
      "slug": "btc-updown-5m-1783644300",
      "strategy": "P2A",
      "side": "DOWN",
      "entry": 0.63,
      "elapsed": 282,
      "result": "win",
      "net_pnl": 0.5673,
      "slip_pnl": 0.4952,
      "winner": "DOWN",
      "mode": "paper",
      "time": "2026-07-10 01:22:40 UTC"
    },
    {
      "market": 17,
      "slug": "btc-updown-5m-1783644600",
      "strategy": "TIGHT",
      "side": "UP",
      "entry": 0.18,
      "elapsed": 188,
      "result": "loss",
      "net_pnl": -1.02,
      "slip_pnl": -1.02,
      "winner": "DOWN",
      "mode": "paper",
      "time": "2026-07-10 01:22:40 UTC"
    },
    {
      "market": 17,
      "slug": "btc-updown-5m-1783644900",
      "strategy": "TIGHT",
      "side": "DOWN",
      "entry": 0.07,
      "elapsed": 153,
      "result": "loss",
      "net_pnl": -1.02,
      "slip_pnl": -1.02,
      "winner": "UP",
      "mode": "paper",
      "time": "2026-07-10 01:22:40 UTC"
    },
    {
      "market": 17,
      "slug": "btc-updown-5m-1783645200",
      "strategy": "TIGHT",
      "side": "DOWN",
      "entry": 0.79,
      "elapsed": 119,
      "result": "win",
      "net_pnl": 0.2458,
      "slip_pnl": 0.1995,
      "winner": "DOWN",
      "mode": "paper",
      "time": "2026-07-10 01:22:40 UTC"
    },
    {
      "market": 17,
      "slug": "btc-updown-5m-1783645200",
      "strategy": "CONSENSUS_3",
      "side": "DOWN",
      "entry": 0.79,
      "elapsed": 119,
      "result": "win",
      "net_pnl": 0.2458,
      "slip_pnl": 0.1995,
      "winner": "DOWN",
      "mode": "paper",
      "time": "2026-07-10 01:22:40 UTC"
    },
    {
      "market": 17,
      "slug": "btc-updown-5m-1783645200",
      "strategy": "SECOND",
      "side": "DOWN",
      "entry": 0.79,
      "elapsed": 119,
      "result": "win",
      "net_pnl": 0.2458,
      "slip_pnl": 0.1995,
      "winner": "DOWN",
      "mode": "paper",
      "time": "2026-07-10 01:22:40 UTC"
    },
    {
      "market": 17,
      "slug": "btc-updown-5m-1783645500",
      "strategy": "SECOND",
      "side": "DOWN",
      "entry": 0.15,
      "elapsed": 115,
      "result": "loss",
      "net_pnl": -1.02,
      "slip_pnl": -1.02,
      "winner": "UP",
      "mode": "paper",
      "time": "2026-07-10 01:22:40 UTC"
    },
    {
      "market": 17,
      "slug": "btc-updown-5m-1783645500",
      "strategy": "TIGHT",
      "side": "DOWN",
      "entry": 0.13,
      "elapsed": 115,
      "result": "loss",
      "net_pnl": -1.02,
      "slip_pnl": -1.02,
      "winner": "UP",
      "mode": "paper",
      "time": "2026-07-10 01:22:40 UTC"
    },
    {
      "market": 17,
      "slug": "btc-updown-5m-1783645500",
      "strategy": "CONSENSUS_3",
      "side": "DOWN",
      "entry": 0.11,
      "elapsed": 115,
      "result": "loss",
      "net_pnl": -1.02,
      "slip_pnl": -1.02,
      "winner": "UP",
      "mode": "paper",
      "time": "2026-07-10 01:22:40 UTC"
    },
    {
      "market": 17,
      "slug": "btc-updown-5m-1783645500",
      "strategy": "SECOND_TIERED",
      "side": "DOWN",
      "entry": 0.11,
      "elapsed": 116,
      "result": "loss",
      "net_pnl": -1.02,
      "slip_pnl": -1.02,
      "winner": "UP",
      "mode": "paper",
      "time": "2026-07-10 01:22:40 UTC"
    },
    {
      "market": 17,
      "slug": "btc-updown-5m-1783645800",
      "strategy": "SECOND_TIERED",
      "side": "DOWN",
      "entry": 0.09,
      "elapsed": 113,
      "result": "loss",
      "net_pnl": -1.02,
      "slip_pnl": -1.02,
      "winner": "UP",
      "mode": "paper",
      "time": "2026-07-10 01:22:40 UTC"
    },
    {
      "market": 17,
      "slug": "btc-updown-5m-1783645800",
      "strategy": "CONSENSUS_3",
      "side": "DOWN",
      "entry": 0.09,
      "elapsed": 113,
      "result": "loss",
      "net_pnl": -1.02,
      "slip_pnl": -1.02,
      "winner": "UP",
      "mode": "paper",
      "time": "2026-07-10 01:22:40 UTC"
    },
    {
      "market": 17,
      "slug": "btc-updown-5m-1783645800",
      "strategy": "SECOND",
      "side": "DOWN",
      "entry": 0.09,
      "elapsed": 113,
      "result": "loss",
      "net_pnl": -1.02,
      "slip_pnl": -1.02,
      "winner": "UP",
      "mode": "paper",
      "time": "2026-07-10 01:22:40 UTC"
    },
    {
      "market": 17,
      "slug": "btc-updown-5m-1783645800",
      "strategy": "TIGHT",
      "side": "DOWN",
      "entry": 0.13,
      "elapsed": 123,
      "result": "loss",
      "net_pnl": -1.02,
      "slip_pnl": -1.02,
      "winner": "UP",
      "mode": "paper",
      "time": "2026-07-10 01:22:40 UTC"
    },
    {
      "market": 17,
      "slug": "btc-updown-5m-1783646100",
      "strategy": "HOUR_REFINED",
      "side": "UP",
      "entry": 0.65,
      "elapsed": 72,
      "result": "win",
      "net_pnl": 0.5185,
      "slip_pnl": 0.4506,
      "winner": "UP",
      "mode": "paper",
      "time": "2026-07-10 01:22:40 UTC"
    },
    {
      "market": 17,
      "slug": "btc-updown-5m-1783646100",
      "strategy": "EARLY_TIMING",
      "side": "UP",
      "entry": 0.69,
      "elapsed": 81,
      "result": "win",
      "net_pnl": 0.4293,
      "slip_pnl": 0.3689,
      "winner": "UP",
      "mode": "paper",
      "time": "2026-07-10 01:22:40 UTC"
    },
    {
      "market": 17,
      "slug": "btc-updown-5m-1783646100",
      "strategy": "CONSENSUS_3",
      "side": "UP",
      "entry": 0.69,
      "elapsed": 82,
      "result": "win",
      "net_pnl": 0.4293,
      "slip_pnl": 0.3689,
      "winner": "UP",
      "mode": "paper",
      "time": "2026-07-10 01:22:40 UTC"
    },
    {
      "market": 17,
      "slug": "btc-updown-5m-1783646100",
      "strategy": "TIGHT",
      "side": "UP",
      "entry": 0.65,
      "elapsed": 84,
      "result": "win",
      "net_pnl": 0.5185,
      "slip_pnl": 0.4506,
      "winner": "UP",
      "mode": "paper",
      "time": "2026-07-10 01:22:40 UTC"
    },
    {
      "market": 17,
      "slug": "btc-updown-5m-1783646400",
      "strategy": "HOUR_REFINED",
      "side": "UP",
      "entry": 0.81,
      "elapsed": 60,
      "result": "pending",
      "net_pnl": null,
      "slip_pnl": null,
      "winner": "",
      "mode": "paper",
      "time": "2026-07-10 01:22:40 UTC"
    },
    {
      "market": 17,
      "slug": "btc-updown-5m-1783646400",
      "strategy": "CONSENSUS_3",
      "side": "UP",
      "entry": 0.81,
      "elapsed": 60,
      "result": "pending",
      "net_pnl": null,
      "slip_pnl": null,
      "winner": "",
      "mode": "paper",
      "time": "2026-07-10 01:22:40 UTC"
    },
    {
      "market": 17,
      "slug": "btc-updown-5m-1783646400",
      "strategy": "TIGHT",
      "side": "UP",
      "entry": 0.83,
      "elapsed": 62,
      "result": "pending",
      "net_pnl": null,
      "slip_pnl": null,
      "winner": "",
      "mode": "paper",
      "time": "2026-07-10 01:22:40 UTC"
    },
    {
      "market": 17,
      "slug": "btc-updown-5m-1783646400",
      "strategy": "EARLY_TIMING",
      "side": "UP",
      "entry": 0.77,
      "elapsed": 80,
      "result": "pending",
      "net_pnl": null,
      "slip_pnl": null,
      "winner": "",
      "mode": "paper",
      "time": "2026-07-10 01:22:40 UTC"
    },
    {
      "market": 17,
      "slug": "btc-updown-5m-1783646400",
      "strategy": "SECOND",
      "side": "UP",
      "entry": 0.74,
      "elapsed": 90,
      "result": "pending",
      "net_pnl": null,
      "slip_pnl": null,
      "winner": "",
      "mode": "paper",
      "time": "2026-07-10 01:22:40 UTC"
    },
    {
      "market": 17,
      "slug": "btc-updown-5m-1783641900",
      "strategy": "P2A",
      "side": "UP",
      "entry": 0.71,
      "elapsed": 266,
      "result": "win",
      "net_pnl": 0.3885,
      "slip_pnl": 0.3314,
      "winner": "UP",
      "mode": "paper",
      "time": "2026-07-10 01:22:37 UTC"
    },
    {
      "market": 16,
      "slug": "btc-updown-5m-1783641600",
      "strategy": "P2A",
      "side": "DOWN",
      "entry": 0.87,
      "elapsed": 261,
      "result": "win",
      "net_pnl": 0.1294,
      "slip_pnl": 0.0911,
      "winner": "DOWN",
      "mode": "paper",
      "time": "2026-07-10 01:20:01 UTC"
    },
    {
      "market": 16,
      "slug": "btc-updown-5m-1783641300",
      "strategy": "TIGHT",
      "side": "DOWN",
      "entry": 0.83,
      "elapsed": 166,
      "result": "win",
      "net_pnl": 0.1848,
      "slip_pnl": 0.1428,
      "winner": "DOWN",
      "mode": "paper",
      "time": "2026-07-10 01:19:21 UTC"
    },
    {
      "market": 16,
      "slug": "btc-updown-5m-1783641000",
      "strategy": "P2A",
      "side": "UP",
      "entry": 0.7,
      "elapsed": 265,
      "result": "win",
      "net_pnl": 0.4086,
      "slip_pnl": 0.3499,
      "winner": "UP",
      "mode": "paper",
      "time": "2026-07-10 01:19:18 UTC"
    },
    {
      "market": 16,
      "slug": "btc-updown-5m-1783640700",
      "strategy": "TIGHT",
      "side": "UP",
      "entry": 0.15,
      "elapsed": 147,
      "result": "loss",
      "net_pnl": -1.02,
      "slip_pnl": -1.02,
      "winner": "DOWN",
      "mode": "paper",
      "time": "2026-07-10 01:15:11 UTC"
    },
    {
      "market": 16,
      "slug": "btc-updown-5m-1783640400",
      "strategy": "P2A",
      "side": "UP",
      "entry": 0.79,
      "elapsed": 266,
      "result": "win",
      "net_pnl": 0.2458,
      "slip_pnl": 0.1995,
      "winner": "UP",
      "mode": "paper",
      "time": "2026-07-10 01:15:08 UTC"
    },
    {
      "market": 15,
      "slug": "btc-updown-5m-1783640100",
      "strategy": "TIGHT",
      "side": "DOWN",
      "entry": 0.13,
      "elapsed": 157,
      "result": "loss",
      "net_pnl": -1.02,
      "slip_pnl": -1.02,
      "winner": "UP",
      "mode": "paper",
      "time": "2026-07-10 01:15:01 UTC"
    },
    {
      "market": 14,
      "slug": "btc-updown-5m-1783639800",
      "strategy": "TIGHT",
      "side": "DOWN",
      "entry": 0.82,
      "elapsed": 108,
      "result": "win",
      "net_pnl": 0.1995,
      "slip_pnl": 0.1565,
      "winner": "DOWN",
      "mode": "paper",
      "time": "2026-07-10 01:10:01 UTC"
    },
    {
      "market": 12,
      "slug": "btc-updown-5m-1783639500",
      "strategy": "P2A",
      "side": "DOWN",
      "entry": 0.81,
      "elapsed": 260,
      "result": "win",
      "net_pnl": 0.2146,
      "slip_pnl": 0.1705,
      "winner": "DOWN",
      "mode": "paper",
      "time": "2026-07-10 01:00:02 UTC"
    },
    {
      "market": 6,
      "slug": "btc-updown-5m-1783639200",
      "strategy": "TIGHT",
      "side": "DOWN",
      "entry": 0.74,
      "elapsed": 130,
      "result": "loss",
      "net_pnl": -1.02,
      "slip_pnl": -1.02,
      "winner": "UP",
      "mode": "paper",
      "time": "2026-07-10 00:29:59 UTC"
    },
    {
      "market": 6,
      "slug": "btc-updown-5m-1783638900",
      "strategy": "TIGHT",
      "side": "DOWN",
      "entry": 0.72,
      "elapsed": 103,
      "result": "win",
      "net_pnl": 0.3689,
      "slip_pnl": 0.3133,
      "winner": "DOWN",
      "mode": "paper",
      "time": "2026-07-10 00:29:20 UTC"
    },
    {
      "market": 5,
      "slug": "btc-updown-5m-1783638300",
      "strategy": "TIGHT",
      "side": "UP",
      "entry": 0.16,
      "elapsed": 123,
      "result": "loss",
      "net_pnl": -1.02,
      "slip_pnl": -1.02,
      "winner": "DOWN",
      "mode": "paper",
      "time": "2026-07-10 00:20:44 UTC"
    },
    {
      "market": 5,
      "slug": "btc-updown-5m-1783636500",
      "strategy": "P2A",
      "side": "DOWN",
      "entry": 0.73,
      "elapsed": 287,
      "result": "win",
      "net_pnl": 0.3499,
      "slip_pnl": 0.2958,
      "winner": "DOWN",
      "mode": "paper",
      "time": "2026-07-10 00:20:39 UTC"
    },
    {
      "market": 5,
      "slug": "btc-updown-5m-1783637700",
      "strategy": "TIGHT",
      "side": "UP",
      "entry": 0.18,
      "elapsed": 169,
      "result": "loss",
      "net_pnl": -1.02,
      "slip_pnl": -1.02,
      "winner": "DOWN",
      "mode": "paper",
      "time": "2026-07-10 00:20:39 UTC"
    },
    {
      "market": 4,
      "slug": "btc-updown-5m-1783634400",
      "strategy": "EARLY_TIMING",
      "side": "UP",
      "entry": 0.69,
      "elapsed": 80,
      "result": "win",
      "net_pnl": 0.4293,
      "slip_pnl": 0.3689,
      "winner": "UP",
      "mode": "paper",
      "time": "2026-07-10 00:20:04 UTC"
    },
    {
      "market": 4,
      "slug": "btc-updown-5m-1783635000",
      "strategy": "TIGHT",
      "side": "DOWN",
      "entry": 0.74,
      "elapsed": 203,
      "result": "win",
      "net_pnl": 0.3314,
      "slip_pnl": 0.2787,
      "winner": "DOWN",
      "mode": "paper",
      "time": "2026-07-10 00:20:04 UTC"
    },
    {
      "market": 3,
      "slug": "btc-updown-5m-1783634100",
      "strategy": "P2A",
      "side": "UP",
      "entry": 0.8,
      "elapsed": 261,
      "result": "loss",
      "net_pnl": -1.02,
      "slip_pnl": -1.02,
      "winner": "DOWN",
      "mode": "paper",
      "time": "2026-07-10 00:15:04 UTC"
    },
    {
      "market": 2,
      "slug": "btc-updown-5m-1783633500",
      "strategy": "CONSENSUS_3",
      "side": "UP",
      "entry": 0.69,
      "elapsed": 116,
      "result": "win",
      "net_pnl": 0.4293,
      "slip_pnl": 0.3689,
      "winner": "UP",
      "mode": "paper",
      "time": "2026-07-10 00:10:04 UTC"
    },
    {
      "market": 2,
      "slug": "btc-updown-5m-1783633500",
      "strategy": "TIGHT",
      "side": "UP",
      "entry": 0.67,
      "elapsed": 126,
      "result": "win",
      "net_pnl": 0.4725,
      "slip_pnl": 0.4086,
      "winner": "UP",
      "mode": "paper",
      "time": "2026-07-10 00:10:04 UTC"
    },
    {
      "market": 1,
      "slug": "btc-updown-5m-1783633200",
      "strategy": "CHEAP_FLOOR",
      "side": "UP",
      "entry": 0.12,
      "elapsed": 60,
      "result": "loss",
      "net_pnl": -1.02,
      "slip_pnl": -1.02,
      "winner": "DOWN",
      "mode": "paper",
      "time": "2026-07-09 23:59:06 UTC"
    },
    {
      "market": 1,
      "slug": "btc-updown-5m-1783632900",
      "strategy": "P2A",
      "side": "UP",
      "entry": 0.81,
      "elapsed": 260,
      "result": "win",
      "net_pnl": 0.2146,
      "slip_pnl": 0.1705,
      "winner": "UP",
      "mode": "paper",
      "time": "2026-07-09 23:40:02 UTC"
    },
    {
      "market": 1,
      "slug": "btc-updown-5m-1783632600",
      "strategy": "P2A",
      "side": "UP",
      "entry": 0.81,
      "elapsed": 266,
      "result": "win",
      "net_pnl": 0.2146,
      "slip_pnl": 0.1705,
      "winner": "UP",
      "mode": "paper",
      "time": "2026-07-09 23:39:06 UTC"
    },
    {
      "market": 1,
      "slug": "btc-updown-5m-1783632300",
      "strategy": "TIGHT",
      "side": "UP",
      "entry": 0.15,
      "elapsed": 127,
      "result": "loss",
      "net_pnl": -1.02,
      "slip_pnl": -1.02,
      "winner": "DOWN",
      "mode": "paper",
      "time": "2026-07-09 23:39:04 UTC"
    },
    {
      "market": 1,
      "slug": "btc-updown-5m-1783632000",
      "strategy": "TIGHT",
      "side": "UP",
      "entry": 0.13,
      "elapsed": 178,
      "result": "loss",
      "net_pnl": -1.02,
      "slip_pnl": -1.02,
      "winner": "DOWN",
      "mode": "paper",
      "time": "2026-07-09 23:35:02 UTC"
    },
    {
      "market": 1,
      "slug": "btc-updown-5m-1783631400",
      "strategy": "SECOND_TIERED",
      "side": "UP",
      "entry": 0.09,
      "elapsed": 107,
      "result": "loss",
      "net_pnl": -1.02,
      "slip_pnl": -1.02,
      "winner": "DOWN",
      "mode": "paper",
      "time": "2026-07-09 23:34:55 UTC"
    },
    {
      "market": 1,
      "slug": "btc-updown-5m-1783631100",
      "strategy": "P2A",
      "side": "DOWN",
      "entry": 0.77,
      "elapsed": 271,
      "result": "win",
      "net_pnl": 0.2787,
      "slip_pnl": 0.23,
      "winner": "DOWN",
      "mode": "paper",
      "time": "2026-07-09 23:26:00 UTC"
    },
    {
      "market": 1,
      "slug": "btc-updown-5m-1783630800",
      "strategy": "SECOND",
      "side": "DOWN",
      "entry": 0.06,
      "elapsed": 90,
      "result": "loss",
      "net_pnl": -1.02,
      "slip_pnl": -1.02,
      "winner": "UP",
      "mode": "paper",
      "time": "2026-07-09 23:25:02 UTC"
    },
    {
      "market": 265,
      "slug": "btc-updown-5m-1783630500",
      "strategy": "TIGHT",
      "side": "DOWN",
      "entry": 0.05,
      "elapsed": 184,
      "result": "loss",
      "net_pnl": -1.02,
      "slip_pnl": -1.02,
      "winner": "UP",
      "mode": "paper",
      "time": "2026-07-09 22:05:02 UTC"
    },
    {
      "market": 263,
      "slug": "btc-updown-5m-1783629600",
      "strategy": "P2A",
      "side": "UP",
      "entry": 0.89,
      "elapsed": 272,
      "result": "win",
      "net_pnl": 0.1036,
      "slip_pnl": 0.067,
      "winner": "UP",
      "mode": "paper",
      "time": "2026-07-09 21:55:02 UTC"
    },
    {
      "market": 262,
      "slug": "btc-updown-5m-1783629300",
      "strategy": "P2A",
      "side": "DOWN",
      "entry": 0.74,
      "elapsed": 261,
      "result": "win",
      "net_pnl": 0.3314,
      "slip_pnl": 0.2787,
      "winner": "DOWN",
      "mode": "paper",
      "time": "2026-07-09 21:50:02 UTC"
    },
    {
      "market": 262,
      "slug": "btc-updown-5m-1783629000",
      "strategy": "TIGHT",
      "side": "DOWN",
      "entry": 0.15,
      "elapsed": 170,
      "result": "loss",
      "net_pnl": -1.02,
      "slip_pnl": -1.02,
      "winner": "UP",
      "mode": "paper",
      "time": "2026-07-09 21:48:06 UTC"
    },
    {
      "market": 262,
      "slug": "btc-updown-5m-1783628700",
      "strategy": "TIGHT",
      "side": "UP",
      "entry": 0.7,
      "elapsed": 108,
      "result": "win",
      "net_pnl": 0.4086,
      "slip_pnl": 0.3499,
      "winner": "UP",
      "mode": "paper",
      "time": "2026-07-09 21:48:04 UTC"
    },
    {
      "market": 261,
      "slug": "btc-updown-5m-1783628400",
      "strategy": "TIGHT",
      "side": "DOWN",
      "entry": 0.14,
      "elapsed": 193,
      "result": "loss",
      "net_pnl": -1.02,
      "slip_pnl": -1.02,
      "winner": "UP",
      "mode": "paper",
      "time": "2026-07-09 21:43:59 UTC"
    },
    {
      "market": 260,
      "slug": "btc-updown-5m-1783627800",
      "strategy": "P2A",
      "side": "DOWN",
      "entry": 0.84,
      "elapsed": 266,
      "result": "win",
      "net_pnl": 0.1705,
      "slip_pnl": 0.1294,
      "winner": "DOWN",
      "mode": "paper",
      "time": "2026-07-09 21:40:04 UTC"
    },
    {
      "market": 259,
      "slug": "btc-updown-5m-1783627500",
      "strategy": "TIGHT",
      "side": "DOWN",
      "entry": 0.18,
      "elapsed": 153,
      "result": "loss",
      "net_pnl": -1.02,
      "slip_pnl": -1.02,
      "winner": "UP",
      "mode": "paper",
      "time": "2026-07-09 21:34:59 UTC"
    },
    {
      "market": 259,
      "slug": "btc-updown-5m-1783627200",
      "strategy": "TIGHT",
      "side": "DOWN",
      "entry": 0.68,
      "elapsed": 138,
      "result": "win",
      "net_pnl": 0.4506,
      "slip_pnl": 0.3885,
      "winner": "DOWN",
      "mode": "paper",
      "time": "2026-07-09 21:30:33 UTC"
    },
    {
      "market": 258,
      "slug": "btc-updown-5m-1783626600",
      "strategy": "P2A",
      "side": "DOWN",
      "entry": 0.66,
      "elapsed": 277,
      "result": "loss",
      "net_pnl": -1.02,
      "slip_pnl": -1.02,
      "winner": "UP",
      "mode": "paper",
      "time": "2026-07-09 21:30:01 UTC"
    },
    {
      "market": 256,
      "slug": "btc-updown-5m-1783626300",
      "strategy": "CONSENSUS_3",
      "side": "DOWN",
      "entry": 0.67,
      "elapsed": 77,
      "result": "win",
      "net_pnl": 0.4725,
      "slip_pnl": 0.4086,
      "winner": "DOWN",
      "mode": "paper",
      "time": "2026-07-09 21:18:47 UTC"
    },
    {
      "market": 256,
      "slug": "btc-updown-5m-1783625700",
      "strategy": "P2A",
      "side": "UP",
      "entry": 0.91,
      "elapsed": 261,
      "result": "win",
      "net_pnl": 0.0789,
      "slip_pnl": 0.0438,
      "winner": "UP",
      "mode": "paper",
      "time": "2026-07-09 21:18:38 UTC"
    },
    {
      "market": 256,
      "slug": "btc-updown-5m-1783625100",
      "strategy": "TIGHT",
      "side": "DOWN",
      "entry": 0.13,
      "elapsed": 153,
      "result": "loss",
      "net_pnl": -1.02,
      "slip_pnl": -1.02,
      "winner": "UP",
      "mode": "paper",
      "time": "2026-07-09 21:18:33 UTC"
    },
    {
      "market": 256,
      "slug": "btc-updown-5m-1783624800",
      "strategy": "P2A",
      "side": "UP",
      "entry": 0.8,
      "elapsed": 261,
      "result": "win",
      "net_pnl": 0.23,
      "slip_pnl": 0.1848,
      "winner": "UP",
      "mode": "paper",
      "time": "2026-07-09 21:18:29 UTC"
    },
    {
      "market": 255,
      "slug": "btc-updown-5m-1783624500",
      "strategy": "P2A",
      "side": "UP",
      "entry": 0.62,
      "elapsed": 260,
      "result": "loss",
      "net_pnl": -1.02,
      "slip_pnl": -1.02,
      "winner": "DOWN",
      "mode": "paper",
      "time": "2026-07-09 21:15:01 UTC"
    },
    {
      "market": 254,
      "slug": "btc-updown-5m-1783624200",
      "strategy": "HOUR",
      "side": "UP",
      "entry": 0.16,
      "elapsed": 66,
      "result": "loss",
      "net_pnl": -1.02,
      "slip_pnl": -1.02,
      "winner": "DOWN",
      "mode": "paper",
      "time": "2026-07-09 21:10:05 UTC"
    },
    {
      "market": 254,
      "slug": "btc-updown-5m-1783623600",
      "strategy": "P2A",
      "side": "DOWN",
      "entry": 0.69,
      "elapsed": 261,
      "result": "loss",
      "net_pnl": -1.02,
      "slip_pnl": -1.02,
      "winner": "UP",
      "mode": "paper",
      "time": "2026-07-09 21:05:14 UTC"
    },
    {
      "market": 254,
      "slug": "btc-updown-5m-1783623900",
      "strategy": "P2A",
      "side": "DOWN",
      "entry": 0.84,
      "elapsed": 271,
      "result": "loss",
      "net_pnl": -1.02,
      "slip_pnl": -1.02,
      "winner": "UP",
      "mode": "paper",
      "time": "2026-07-09 21:05:11 UTC"
    },
    {
      "market": 253,
      "slug": "btc-updown-5m-1783623300",
      "strategy": "P2A",
      "side": "DOWN",
      "entry": 0.77,
      "elapsed": 282,
      "result": "win",
      "net_pnl": 0.2787,
      "slip_pnl": 0.23,
      "winner": "DOWN",
      "mode": "paper",
      "time": "2026-07-09 21:05:08 UTC"
    },
    {
      "market": 253,
      "slug": "btc-updown-5m-1783623000",
      "strategy": "TIGHT",
      "side": "UP",
      "entry": 0.11,
      "elapsed": 133,
      "result": "loss",
      "net_pnl": -1.02,
      "slip_pnl": -1.02,
      "winner": "DOWN",
      "mode": "paper",
      "time": "2026-07-09 21:05:01 UTC"
    },
    {
      "market": 249,
      "slug": "btc-updown-5m-1783622400",
      "strategy": "TIGHT",
      "side": "DOWN",
      "entry": 0.13,
      "elapsed": 152,
      "result": "loss",
      "net_pnl": -1.02,
      "slip_pnl": -1.02,
      "winner": "UP",
      "mode": "paper",
      "time": "2026-07-09 20:44:59 UTC"
    }
  ]
}