{
  "last_updated": "2026-03-30 04:19:56 UTC",
  "summary": {
    "total_pnl": -2.12,
    "markets_traded": 3,
    "wins": 2,
    "losses": 1,
    "win_rate": 66.7,
    "best_trade": 0.78,
    "worst_trade": -3.32,
    "daily_stop_loss_hit": false,
    "mode": "paper"
  },
  "trades": [
    {
      "market": 52,
      "time": "2026-03-30 04:15:00 UTC",
      "phases": "Phase 1 + Phase 2 + Phase 3",
      "outcome": "P1: no trigger | P2: skipped \u2014 UP mid 0.4350 out of range | P3: snipe win @ $0.9900",
      "pnl": 0.42,
      "mode": "paper",
      "running_pnl": -2.12
    },
    {
      "market": 51,
      "time": "2026-03-30 04:10:00 UTC",
      "phases": "Phase 1 + Phase 2 + Phase 3",
      "outcome": "P1: no trigger | P2: round trip complete | P3: snipe win @ $0.9250",
      "pnl": 0.78,
      "mode": "paper",
      "running_pnl": -2.54
    },
    {
      "market": 50,
      "time": "2026-03-30 04:05:00 UTC",
      "phases": "Phase 1 + Phase 2 + Phase 3",
      "outcome": "P1: no trigger | P2: buy(s) filled \u2014 stop loss exit | P3: snipe win @ $0.9900",
      "pnl": -3.32,
      "mode": "paper",
      "running_pnl": -3.32
    }
  ]
}