{
  "last_updated": "2026-04-11 14:49:59 UTC",
  "summary": {
    "total_pnl": -32.55,
    "markets_traded": 28,
    "wins": 15,
    "losses": 13,
    "win_rate": 53.6,
    "best_trade": 5.11,
    "worst_trade": -7.86,
    "daily_stop_loss_hit": false,
    "mode": "paper",
    "p1w_wins": 3,
    "p1w_losses": 0,
    "p1w_pnl": 5.98,
    "p1l_wins": 2,
    "p1l_losses": 2,
    "p1l_pnl": 0.13,
    "p2a_wins": 8,
    "p2a_losses": 2,
    "p2a_pnl": 2.12,
    "p3_wins": 16,
    "p3_losses": 12,
    "p3_pnl": -40.78,
    "p1w_win_rate": 100.0,
    "p1l_win_rate": 50.0,
    "p2a_win_rate": 80.0,
    "p3_win_rate": 57.1
  },
  "trades": [
    {
      "market": 178,
      "time": "2026-04-11 14:45:00 UTC",
      "phases": "Phase 1 + Phase 2A + Phase 3",
      "outcome": "P1: no trigger | P2A: momentum stop loss @ $0.1100 | P3: snipe loss @ $0.2600 (stop loss), continued down to 0.0600",
      "pnl": -7.86,
      "mode": "paper",
      "running_pnl": -32.55,
      "p1_winner_pnl": 0.0,
      "p1_loser_pnl": 0.0,
      "p2a_pnl": -4.25,
      "p3_pnl": -3.62,
      "p1_bet_type": null,
      "p1_outcome": "no trigger",
      "p2a_outcome": "momentum stop loss @ $0.1100",
      "p3_outcome": "snipe loss @ $0.2600 (stop loss), continued down to 0.0600",
      "p1w_result": "no trigger",
      "p1l_result": "no trigger",
      "p2a_result": "loss",
      "p3_result": "loss"
    },
    {
      "market": 177,
      "time": "2026-04-11 14:40:00 UTC",
      "phases": "Phase 1 + Phase 2A + Phase 3",
      "outcome": "P1: take profit @ $0.9000 | P2A: no momentum signal | P3: snipe win @ $0.9900",
      "pnl": 5.11,
      "mode": "paper",
      "running_pnl": -24.68,
      "p1_winner_pnl": 0.0,
      "p1_loser_pnl": 4.9,
      "p2a_pnl": 0.0,
      "p3_pnl": 0.21,
      "p1_bet_type": "loser",
      "p1_outcome": "directional win",
      "p2a_outcome": "no momentum signal",
      "p3_outcome": "snipe win @ $0.9900",
      "p1w_result": "no trigger",
      "p1l_result": "win",
      "p2a_result": "no trigger",
      "p3_result": "win"
    },
    {
      "market": 176,
      "time": "2026-04-11 14:35:00 UTC",
      "phases": "Phase 1 + Phase 2A + Phase 3",
      "outcome": "P1: no trigger | P2A: no momentum signal | P3: snipe loss @ $0.0800 (stop loss), continued down to 0.0010",
      "pnl": -4.58,
      "mode": "paper",
      "running_pnl": -29.79,
      "p1_winner_pnl": 0.0,
      "p1_loser_pnl": 0.0,
      "p2a_pnl": 0.0,
      "p3_pnl": -4.58,
      "p1_bet_type": null,
      "p1_outcome": "no trigger",
      "p2a_outcome": "no momentum signal",
      "p3_outcome": "snipe loss @ $0.0800 (stop loss), continued down to 0.0010",
      "p1w_result": "no trigger",
      "p1l_result": "no trigger",
      "p2a_result": "no trigger",
      "p3_result": "loss"
    },
    {
      "market": 175,
      "time": "2026-04-11 14:30:00 UTC",
      "phases": "Phase 1 + Phase 2A + Phase 3",
      "outcome": "P1: no trigger | P2A: momentum win @ $0.9900 | P3: snipe win @ $0.9900",
      "pnl": 1.12,
      "mode": "paper",
      "running_pnl": -25.22,
      "p1_winner_pnl": 0.0,
      "p1_loser_pnl": 0.0,
      "p2a_pnl": 0.62,
      "p3_pnl": 0.5,
      "p1_bet_type": null,
      "p1_outcome": "no trigger",
      "p2a_outcome": "momentum win @ $0.9900",
      "p3_outcome": "snipe win @ $0.9900",
      "p1w_result": "no trigger",
      "p1l_result": "no trigger",
      "p2a_result": "win",
      "p3_result": "win"
    },
    {
      "market": 174,
      "time": "2026-04-11 14:25:00 UTC",
      "phases": "Phase 1 + Phase 2A + Phase 3",
      "outcome": "P1: directional loss @ $0.0200 | P2A: momentum win @ $0.9900 | P3: snipe win @ $0.9900",
      "pnl": -2.93,
      "mode": "paper",
      "running_pnl": -26.34,
      "p1_winner_pnl": 0.0,
      "p1_loser_pnl": -4.78,
      "p2a_pnl": 1.35,
      "p3_pnl": 0.5,
      "p1_bet_type": "loser",
      "p1_outcome": "directional loss",
      "p2a_outcome": "momentum win @ $0.9900",
      "p3_outcome": "snipe win @ $0.9900",
      "p1w_result": "no trigger",
      "p1l_result": "loss",
      "p2a_result": "win",
      "p3_result": "win"
    },
    {
      "market": 173,
      "time": "2026-04-11 14:20:00 UTC",
      "phases": "Phase 1 + Phase 2A + Phase 3",
      "outcome": "P1: no trigger | P2A: momentum win @ $0.9900 | P3: snipe win @ $0.9900",
      "pnl": 1.06,
      "mode": "paper",
      "running_pnl": -23.41,
      "p1_winner_pnl": 0.0,
      "p1_loser_pnl": 0.0,
      "p2a_pnl": 0.56,
      "p3_pnl": 0.5,
      "p1_bet_type": null,
      "p1_outcome": "no trigger",
      "p2a_outcome": "momentum win @ $0.9900",
      "p3_outcome": "snipe win @ $0.9900",
      "p1w_result": "no trigger",
      "p1l_result": "no trigger",
      "p2a_result": "win",
      "p3_result": "win"
    },
    {
      "market": 172,
      "time": "2026-04-11 14:15:00 UTC",
      "phases": "Phase 1 + Phase 2A + Phase 3",
      "outcome": "P1: directional loss @ $0.0100 | P2A: no momentum signal | P3: snipe win @ $0.9900",
      "pnl": -4.63,
      "mode": "paper",
      "running_pnl": -24.47,
      "p1_winner_pnl": 0.0,
      "p1_loser_pnl": -4.89,
      "p2a_pnl": 0.0,
      "p3_pnl": 0.27,
      "p1_bet_type": "loser",
      "p1_outcome": "directional loss",
      "p2a_outcome": "no momentum signal",
      "p3_outcome": "snipe win @ $0.9900",
      "p1w_result": "no trigger",
      "p1l_result": "loss",
      "p2a_result": "no trigger",
      "p3_result": "win"
    },
    {
      "market": 171,
      "time": "2026-04-11 14:10:00 UTC",
      "phases": "Phase 1 + Phase 2A + Phase 3",
      "outcome": "P1: no trigger | P2A: momentum win @ $0.9900 | P3: snipe loss @ $0.4100 (stop loss), continued down to 0.0100",
      "pnl": -1.85,
      "mode": "paper",
      "running_pnl": -19.84,
      "p1_winner_pnl": 0.0,
      "p1_loser_pnl": 0.0,
      "p2a_pnl": 0.89,
      "p3_pnl": -2.75,
      "p1_bet_type": null,
      "p1_outcome": "no trigger",
      "p2a_outcome": "momentum win @ $0.9900",
      "p3_outcome": "snipe loss @ $0.4100 (stop loss), continued down to 0.0100",
      "p1w_result": "no trigger",
      "p1l_result": "no trigger",
      "p2a_result": "win",
      "p3_result": "loss"
    },
    {
      "market": 170,
      "time": "2026-04-11 14:05:00 UTC",
      "phases": "Phase 1 + Phase 2A + Phase 3",
      "outcome": "P1: take profit @ $0.9000 | P2A: no momentum signal | P3: snipe loss @ $0.1200 (stop loss), continued down to 0.0100",
      "pnl": -2.24,
      "mode": "paper",
      "running_pnl": -17.99,
      "p1_winner_pnl": 2.1,
      "p1_loser_pnl": 0.0,
      "p2a_pnl": 0.0,
      "p3_pnl": -4.33,
      "p1_bet_type": "winner",
      "p1_outcome": "directional win",
      "p2a_outcome": "no momentum signal",
      "p3_outcome": "snipe loss @ $0.1200 (stop loss), continued down to 0.0100",
      "p1w_result": "win",
      "p1l_result": "no trigger",
      "p2a_result": "no trigger",
      "p3_result": "loss"
    },
    {
      "market": 169,
      "time": "2026-04-11 14:00:00 UTC",
      "phases": "Phase 1 + Phase 2A + Phase 3",
      "outcome": "P1: no trigger | P2A: momentum win @ $0.9900 | P3: snipe loss @ $0.0500 (stop loss), continued down to 0.0200",
      "pnl": -3.47,
      "mode": "paper",
      "running_pnl": -15.75,
      "p1_winner_pnl": 0.0,
      "p1_loser_pnl": 0.0,
      "p2a_pnl": 1.27,
      "p3_pnl": -4.73,
      "p1_bet_type": null,
      "p1_outcome": "no trigger",
      "p2a_outcome": "momentum win @ $0.9900",
      "p3_outcome": "snipe loss @ $0.0500 (stop loss), continued down to 0.0200",
      "p1w_result": "no trigger",
      "p1l_result": "no trigger",
      "p2a_result": "win",
      "p3_result": "loss"
    },
    {
      "market": 168,
      "time": "2026-04-11 13:55:00 UTC",
      "phases": "Phase 1 + Phase 2A + Phase 3",
      "outcome": "P1: no trigger | P2A: momentum win @ $0.9900 | P3: snipe loss @ $0.2100 (stop loss), continued down to 0.0100",
      "pnl": -0.85,
      "mode": "paper",
      "running_pnl": -12.28,
      "p1_winner_pnl": 0.0,
      "p1_loser_pnl": 0.0,
      "p2a_pnl": 2.98,
      "p3_pnl": -3.83,
      "p1_bet_type": null,
      "p1_outcome": "no trigger",
      "p2a_outcome": "momentum win @ $0.9900",
      "p3_outcome": "snipe loss @ $0.2100 (stop loss), continued down to 0.0100",
      "p1w_result": "no trigger",
      "p1l_result": "no trigger",
      "p2a_result": "win",
      "p3_result": "loss"
    },
    {
      "market": 167,
      "time": "2026-04-11 13:50:00 UTC",
      "phases": "Phase 1 + Phase 2A + Phase 3",
      "outcome": "P1: no trigger | P2A: no momentum signal | P3: snipe win @ $0.9900",
      "pnl": 0.5,
      "mode": "paper",
      "running_pnl": -11.43,
      "p1_winner_pnl": 0.0,
      "p1_loser_pnl": 0.0,
      "p2a_pnl": 0.0,
      "p3_pnl": 0.5,
      "p1_bet_type": null,
      "p1_outcome": "no trigger",
      "p2a_outcome": "no momentum signal",
      "p3_outcome": "snipe win @ $0.9900",
      "p1w_result": "no trigger",
      "p1l_result": "no trigger",
      "p2a_result": "no trigger",
      "p3_result": "win"
    },
    {
      "market": 166,
      "time": "2026-04-11 13:45:00 UTC",
      "phases": "Phase 1 + Phase 2A + Phase 3",
      "outcome": "P1: no trigger | P2A: no momentum signal | P3: snipe loss @ $0.3400 (stop loss), continued down to 0.0100",
      "pnl": -3.19,
      "mode": "paper",
      "running_pnl": -11.93,
      "p1_winner_pnl": 0.0,
      "p1_loser_pnl": 0.0,
      "p2a_pnl": 0.0,
      "p3_pnl": -3.19,
      "p1_bet_type": null,
      "p1_outcome": "no trigger",
      "p2a_outcome": "no momentum signal",
      "p3_outcome": "snipe loss @ $0.3400 (stop loss), continued down to 0.0100",
      "p1w_result": "no trigger",
      "p1l_result": "no trigger",
      "p2a_result": "no trigger",
      "p3_result": "loss"
    },
    {
      "market": 165,
      "time": "2026-04-11 13:40:00 UTC",
      "phases": "Phase 1 + Phase 2A + Phase 3",
      "outcome": "P1: no trigger | P2A: no momentum signal | P3: snipe loss @ $0.0400 (stop loss), continued down to 0.0100",
      "pnl": -4.78,
      "mode": "paper",
      "running_pnl": -8.74,
      "p1_winner_pnl": 0.0,
      "p1_loser_pnl": 0.0,
      "p2a_pnl": 0.0,
      "p3_pnl": -4.78,
      "p1_bet_type": null,
      "p1_outcome": "no trigger",
      "p2a_outcome": "no momentum signal",
      "p3_outcome": "snipe loss @ $0.0400 (stop loss), continued down to 0.0100",
      "p1w_result": "no trigger",
      "p1l_result": "no trigger",
      "p2a_result": "no trigger",
      "p3_result": "loss"
    },
    {
      "market": 164,
      "time": "2026-04-11 13:35:00 UTC",
      "phases": "Phase 1 + Phase 2A + Phase 3",
      "outcome": "P1: no trigger | P2A: no momentum signal | P3: snipe win @ $0.9900",
      "pnl": 0.44,
      "mode": "paper",
      "running_pnl": -3.96,
      "p1_winner_pnl": 0.0,
      "p1_loser_pnl": 0.0,
      "p2a_pnl": 0.0,
      "p3_pnl": 0.44,
      "p1_bet_type": null,
      "p1_outcome": "no trigger",
      "p2a_outcome": "no momentum signal",
      "p3_outcome": "snipe win @ $0.9900",
      "p1w_result": "no trigger",
      "p1l_result": "no trigger",
      "p2a_result": "no trigger",
      "p3_result": "win"
    },
    {
      "market": 163,
      "time": "2026-04-11 13:30:00 UTC",
      "phases": "Phase 1 + Phase 2A + Phase 3",
      "outcome": "P1: no trigger | P2A: no momentum signal | P3: snipe win @ $0.9900",
      "pnl": 0.5,
      "mode": "paper",
      "running_pnl": -4.4,
      "p1_winner_pnl": 0.0,
      "p1_loser_pnl": 0.0,
      "p2a_pnl": 0.0,
      "p3_pnl": 0.5,
      "p1_bet_type": null,
      "p1_outcome": "no trigger",
      "p2a_outcome": "no momentum signal",
      "p3_outcome": "snipe win @ $0.9900",
      "p1w_result": "no trigger",
      "p1l_result": "no trigger",
      "p2a_result": "no trigger",
      "p3_result": "win"
    },
    {
      "market": 162,
      "time": "2026-04-11 13:25:00 UTC",
      "phases": "Phase 1 + Phase 2A + Phase 3",
      "outcome": "P1: no trigger | P2A: no momentum signal | P3: snipe loss @ $0.2800 (stop loss), continued down to 0.0100",
      "pnl": -3.44,
      "mode": "paper",
      "running_pnl": -4.9,
      "p1_winner_pnl": 0.0,
      "p1_loser_pnl": 0.0,
      "p2a_pnl": 0.0,
      "p3_pnl": -3.44,
      "p1_bet_type": null,
      "p1_outcome": "no trigger",
      "p2a_outcome": "no momentum signal",
      "p3_outcome": "snipe loss @ $0.2800 (stop loss), continued down to 0.0100",
      "p1w_result": "no trigger",
      "p1l_result": "no trigger",
      "p2a_result": "no trigger",
      "p3_result": "loss"
    },
    {
      "market": 161,
      "time": "2026-04-11 13:20:00 UTC",
      "phases": "Phase 1 + Phase 2A + Phase 3",
      "outcome": "P1: no trigger | P2A: no momentum signal | P3: snipe win @ $0.9900",
      "pnl": 0.5,
      "mode": "paper",
      "running_pnl": -1.46,
      "p1_winner_pnl": 0.0,
      "p1_loser_pnl": 0.0,
      "p2a_pnl": 0.0,
      "p3_pnl": 0.5,
      "p1_bet_type": null,
      "p1_outcome": "no trigger",
      "p2a_outcome": "no momentum signal",
      "p3_outcome": "snipe win @ $0.9900",
      "p1w_result": "no trigger",
      "p1l_result": "no trigger",
      "p2a_result": "no trigger",
      "p3_result": "win"
    },
    {
      "market": 160,
      "time": "2026-04-11 13:15:00 UTC",
      "phases": "Phase 1 + Phase 2A + Phase 3",
      "outcome": "P1: no trigger | P2A: no momentum signal | P3: snipe win @ $0.9900",
      "pnl": 0.5,
      "mode": "paper",
      "running_pnl": -1.96,
      "p1_winner_pnl": 0.0,
      "p1_loser_pnl": 0.0,
      "p2a_pnl": 0.0,
      "p3_pnl": 0.5,
      "p1_bet_type": null,
      "p1_outcome": "no trigger",
      "p2a_outcome": "no momentum signal",
      "p3_outcome": "snipe win @ $0.9900",
      "p1w_result": "no trigger",
      "p1l_result": "no trigger",
      "p2a_result": "no trigger",
      "p3_result": "win"
    },
    {
      "market": 159,
      "time": "2026-04-11 13:10:00 UTC",
      "phases": "Phase 1 + Phase 2A + Phase 3",
      "outcome": "P1: no trigger | P2A: no momentum signal | P3: snipe win @ $0.9990",
      "pnl": 0.55,
      "mode": "paper",
      "running_pnl": -2.46,
      "p1_winner_pnl": 0.0,
      "p1_loser_pnl": 0.0,
      "p2a_pnl": 0.0,
      "p3_pnl": 0.55,
      "p1_bet_type": null,
      "p1_outcome": "no trigger",
      "p2a_outcome": "no momentum signal",
      "p3_outcome": "snipe win @ $0.9990",
      "p1w_result": "no trigger",
      "p1l_result": "no trigger",
      "p2a_result": "no trigger",
      "p3_result": "win"
    },
    {
      "market": 158,
      "time": "2026-04-11 13:05:00 UTC",
      "phases": "Phase 1 + Phase 2A + Phase 3",
      "outcome": "P1: no trigger | P2A: no momentum signal | P3: snipe win @ $0.9900",
      "pnl": 0.27,
      "mode": "paper",
      "running_pnl": -3.01,
      "p1_winner_pnl": 0.0,
      "p1_loser_pnl": 0.0,
      "p2a_pnl": 0.0,
      "p3_pnl": 0.27,
      "p1_bet_type": null,
      "p1_outcome": "no trigger",
      "p2a_outcome": "no momentum signal",
      "p3_outcome": "snipe win @ $0.9900",
      "p1w_result": "no trigger",
      "p1l_result": "no trigger",
      "p2a_result": "no trigger",
      "p3_result": "win"
    },
    {
      "market": 157,
      "time": "2026-04-11 13:00:00 UTC",
      "phases": "Phase 1 + Phase 2A + Phase 3",
      "outcome": "P1: no trigger | P2A: no momentum signal | P3: snipe win @ $0.9900",
      "pnl": 0.5,
      "mode": "paper",
      "running_pnl": -3.27,
      "p1_winner_pnl": 0.0,
      "p1_loser_pnl": 0.0,
      "p2a_pnl": 0.0,
      "p3_pnl": 0.5,
      "p1_bet_type": null,
      "p1_outcome": "no trigger",
      "p2a_outcome": "no momentum signal",
      "p3_outcome": "snipe win @ $0.9900",
      "p1w_result": "no trigger",
      "p1l_result": "no trigger",
      "p2a_result": "no trigger",
      "p3_result": "win"
    },
    {
      "market": 156,
      "time": "2026-04-11 12:55:00 UTC",
      "phases": "Phase 1 + Phase 2A + Phase 3",
      "outcome": "P1: take profit @ $0.9000 | P2A: momentum win @ $0.9900 | P3: snipe win @ $0.9900",
      "pnl": 4.22,
      "mode": "paper",
      "running_pnl": -3.77,
      "p1_winner_pnl": 2.21,
      "p1_loser_pnl": 0.0,
      "p2a_pnl": 1.51,
      "p3_pnl": 0.5,
      "p1_bet_type": "winner",
      "p1_outcome": "directional win",
      "p2a_outcome": "momentum win @ $0.9900",
      "p3_outcome": "snipe win @ $0.9900",
      "p1w_result": "win",
      "p1l_result": "no trigger",
      "p2a_result": "win",
      "p3_result": "win"
    },
    {
      "market": 155,
      "time": "2026-04-11 12:50:00 UTC",
      "phases": "Phase 1 + Phase 2A + Phase 3",
      "outcome": "P1: no trigger | P2A: no momentum signal | P3: snipe win @ $0.9900",
      "pnl": 0.32,
      "mode": "paper",
      "running_pnl": -8.0,
      "p1_winner_pnl": 0.0,
      "p1_loser_pnl": 0.0,
      "p2a_pnl": 0.0,
      "p3_pnl": 0.32,
      "p1_bet_type": null,
      "p1_outcome": "no trigger",
      "p2a_outcome": "no momentum signal",
      "p3_outcome": "snipe win @ $0.9900",
      "p1w_result": "no trigger",
      "p1l_result": "no trigger",
      "p2a_result": "no trigger",
      "p3_result": "win"
    },
    {
      "market": 154,
      "time": "2026-04-11 12:45:00 UTC",
      "phases": "Phase 1 + Phase 2A + Phase 3",
      "outcome": "P1: take profit @ $0.9000 | P2A: momentum win @ $0.9400 | P3: snipe loss @ $0.3600 (stop loss), continued down to 0.1000",
      "pnl": 2.86,
      "mode": "paper",
      "running_pnl": -8.32,
      "p1_winner_pnl": 0.0,
      "p1_loser_pnl": 4.9,
      "p2a_pnl": 1.03,
      "p3_pnl": -3.06,
      "p1_bet_type": "loser",
      "p1_outcome": "directional win",
      "p2a_outcome": "momentum win @ $0.9400",
      "p3_outcome": "snipe loss @ $0.3600 (stop loss), continued down to 0.1000",
      "p1w_result": "no trigger",
      "p1l_result": "win",
      "p2a_result": "win",
      "p3_result": "loss"
    },
    {
      "market": 153,
      "time": "2026-04-11 12:40:00 UTC",
      "phases": "Phase 1 + Phase 2A + Phase 3",
      "outcome": "P1: no trigger | P2A: no momentum signal | P3: snipe loss @ $0.0500 (stop loss), continued down to 0.0100",
      "pnl": -4.73,
      "mode": "paper",
      "running_pnl": -11.18,
      "p1_winner_pnl": 0.0,
      "p1_loser_pnl": 0.0,
      "p2a_pnl": 0.0,
      "p3_pnl": -4.73,
      "p1_bet_type": null,
      "p1_outcome": "no trigger",
      "p2a_outcome": "no momentum signal",
      "p3_outcome": "snipe loss @ $0.0500 (stop loss), continued down to 0.0100",
      "p1w_result": "no trigger",
      "p1l_result": "no trigger",
      "p2a_result": "no trigger",
      "p3_result": "loss"
    },
    {
      "market": 152,
      "time": "2026-04-11 12:35:00 UTC",
      "phases": "Phase 1 + Phase 2A + Phase 3",
      "outcome": "P1: take profit @ $0.9000 | P2A: momentum stop loss @ $0.1800 | P3: snipe loss @ $0.0400",
      "pnl": -6.95,
      "mode": "paper",
      "running_pnl": -6.45,
      "p1_winner_pnl": 1.68,
      "p1_loser_pnl": 0.0,
      "p2a_pnl": -3.85,
      "p3_pnl": -4.78,
      "p1_bet_type": "winner",
      "p1_outcome": "directional win",
      "p2a_outcome": "momentum stop loss @ $0.1800",
      "p3_outcome": "snipe loss @ $0.0400",
      "p1w_result": "win",
      "p1l_result": "no trigger",
      "p2a_result": "loss",
      "p3_result": "loss"
    },
    {
      "market": 151,
      "time": "2026-04-11 12:30:00 UTC",
      "phases": "Phase 1 + Phase 2A + Phase 3",
      "outcome": "P1: no trigger | P2A: no momentum signal | P3: snipe win @ $0.9900",
      "pnl": 0.5,
      "mode": "paper",
      "running_pnl": 0.5,
      "p1_winner_pnl": 0.0,
      "p1_loser_pnl": 0.0,
      "p2a_pnl": 0.0,
      "p3_pnl": 0.5,
      "p1_bet_type": null,
      "p1_outcome": "no trigger",
      "p2a_outcome": "no momentum signal",
      "p3_outcome": "snipe win @ $0.9900",
      "p1w_result": "no trigger",
      "p1l_result": "no trigger",
      "p2a_result": "no trigger",
      "p3_result": "win"
    }
  ]
}