{
  "last_updated": "2026-05-13 13:45:38 UTC",
  "mode": "paper",
  "summary": {
    "total_pnl": 9.485,
    "total_pnl_slip": -37.623,
    "markets_traded": 189,
    "wins": 366,
    "losses": 340,
    "win_rate": 51.8,
    "P1L_pnl": 11.983,
    "P2A_pnl": 1.982,
    "DRIFT_pnl": -6.344,
    "FADE_pnl": -11.504,
    "SQUEEZE_pnl": 13.046,
    "ANCHOR_pnl": 0.321,
    "P1L_pnl_slip": 3.391,
    "P2A_pnl_slip": -0.43,
    "DRIFT_pnl_slip": -16.45,
    "FADE_pnl_slip": -28.809,
    "SQUEEZE_pnl_slip": 5.746,
    "ANCHOR_pnl_slip": -1.07,
    "P1L_wins": 64,
    "P2A_wins": 50,
    "DRIFT_wins": 103,
    "FADE_wins": 55,
    "SQUEEZE_wins": 74,
    "ANCHOR_wins": 20,
    "P1L_losses": 61,
    "P2A_losses": 11,
    "DRIFT_losses": 86,
    "FADE_losses": 132,
    "SQUEEZE_losses": 40,
    "ANCHOR_losses": 10
  },
  "trades": [
    {
      "market": 166,
      "strategy": "P1L",
      "side": "DOWN",
      "entry": 0.48,
      "result": "loss",
      "net_pnl": -1.02,
      "slip_pnl": -1.02,
      "winner": "UP",
      "mode": "paper"
    },
    {
      "market": 166,
      "strategy": "DRIFT",
      "side": "UP",
      "entry": 0.45,
      "result": "win",
      "net_pnl": 1.2022,
      "slip_pnl": 1.0633,
      "winner": "UP",
      "mode": "paper"
    },
    {
      "market": 166,
      "strategy": "FADE",
      "side": "UP",
      "entry": 0.4,
      "result": "win",
      "net_pnl": 1.48,
      "slip_pnl": 1.3056,
      "winner": "UP",
      "mode": "paper"
    },
    {
      "market": 166,
      "strategy": "SQUEEZE",
      "side": "DOWN",
      "entry": 0.29,
      "result": "loss",
      "net_pnl": -1.02,
      "slip_pnl": -1.02,
      "winner": "UP",
      "mode": "paper"
    },
    {
      "market": 166,
      "strategy": "P1L",
      "side": "UP",
      "entry": 0.455,
      "result": "loss",
      "net_pnl": -1.02,
      "slip_pnl": -1.02,
      "winner": "DOWN",
      "mode": "paper"
    },
    {
      "market": 166,
      "strategy": "DRIFT",
      "side": "UP",
      "entry": 0.53,
      "result": "loss",
      "net_pnl": -1.02,
      "slip_pnl": -1.02,
      "winner": "DOWN",
      "mode": "paper"
    },
    {
      "market": 166,
      "strategy": "FADE",
      "side": "DOWN",
      "entry": 0.4,
      "result": "win",
      "net_pnl": 1.48,
      "slip_pnl": 1.3056,
      "winner": "DOWN",
      "mode": "paper"
    },
    {
      "market": 166,
      "strategy": "SQUEEZE",
      "side": "UP",
      "entry": 0.66,
      "result": "loss",
      "net_pnl": -1.02,
      "slip_pnl": -1.02,
      "winner": "DOWN",
      "mode": "paper"
    },
    {
      "market": 166,
      "strategy": "P1L",
      "side": "UP",
      "entry": 0.415,
      "result": "loss",
      "net_pnl": -1.02,
      "slip_pnl": -1.02,
      "winner": "DOWN",
      "mode": "paper"
    },
    {
      "market": 166,
      "strategy": "DRIFT",
      "side": "DOWN",
      "entry": 0.68,
      "result": "win",
      "net_pnl": 0.4506,
      "slip_pnl": 0.3885,
      "winner": "DOWN",
      "mode": "paper"
    },
    {
      "market": 166,
      "strategy": "FADE",
      "side": "DOWN",
      "entry": 0.44,
      "result": "win",
      "net_pnl": 1.2527,
      "slip_pnl": 1.1077,
      "winner": "DOWN",
      "mode": "paper"
    },
    {
      "market": 166,
      "strategy": "SQUEEZE",
      "side": "DOWN",
      "entry": 0.59,
      "result": "win",
      "net_pnl": 0.6749,
      "slip_pnl": 0.5929,
      "winner": "DOWN",
      "mode": "paper"
    },
    {
      "market": 166,
      "strategy": "P2A",
      "side": "UP",
      "entry": 0.52,
      "result": "loss",
      "net_pnl": -1.02,
      "slip_pnl": -1.02,
      "winner": "DOWN",
      "mode": "paper"
    },
    {
      "market": 166,
      "strategy": "P1L",
      "side": "UP",
      "entry": 0.475,
      "result": "loss",
      "net_pnl": -1.02,
      "slip_pnl": -1.02,
      "winner": "DOWN",
      "mode": "paper"
    },
    {
      "market": 166,
      "strategy": "DRIFT",
      "side": "DOWN",
      "entry": 0.68,
      "result": "win",
      "net_pnl": 0.4506,
      "slip_pnl": 0.3885,
      "winner": "DOWN",
      "mode": "paper"
    },
    {
      "market": 166,
      "strategy": "ANCHOR",
      "side": "DOWN",
      "entry": 0.62,
      "result": "win",
      "net_pnl": 0.5929,
      "slip_pnl": 0.5185,
      "winner": "DOWN",
      "mode": "paper"
    },
    {
      "market": 166,
      "strategy": "FADE",
      "side": "UP",
      "entry": 0.24,
      "result": "loss",
      "net_pnl": -1.02,
      "slip_pnl": -1.02,
      "winner": "DOWN",
      "mode": "paper"
    },
    {
      "market": 166,
      "strategy": "P2A",
      "side": "UP",
      "entry": 0.82,
      "result": "loss",
      "net_pnl": -1.02,
      "slip_pnl": -1.02,
      "winner": "DOWN",
      "mode": "paper"
    },
    {
      "market": 166,
      "strategy": "P1L",
      "side": "UP",
      "entry": 0.45,
      "result": "loss",
      "net_pnl": -1.02,
      "slip_pnl": -1.02,
      "winner": "DOWN",
      "mode": "paper"
    },
    {
      "market": 166,
      "strategy": "DRIFT",
      "side": "UP",
      "entry": 0.47,
      "result": "loss",
      "net_pnl": -1.02,
      "slip_pnl": -1.02,
      "winner": "DOWN",
      "mode": "paper"
    },
    {
      "market": 166,
      "strategy": "FADE",
      "side": "UP",
      "entry": 0.29,
      "result": "loss",
      "net_pnl": -1.02,
      "slip_pnl": -1.02,
      "winner": "DOWN",
      "mode": "paper"
    },
    {
      "market": 166,
      "strategy": "P1L",
      "side": "DOWN",
      "entry": 0.49,
      "result": "win",
      "net_pnl": 1.0208,
      "slip_pnl": 0.9031,
      "winner": "DOWN",
      "mode": "paper"
    },
    {
      "market": 166,
      "strategy": "DRIFT",
      "side": "UP",
      "entry": 0.52,
      "result": "loss",
      "net_pnl": -1.02,
      "slip_pnl": -1.02,
      "winner": "DOWN",
      "mode": "paper"
    },
    {
      "market": 166,
      "strategy": "FADE",
      "side": "DOWN",
      "entry": 0.37,
      "result": "win",
      "net_pnl": 1.6827,
      "slip_pnl": 1.48,
      "winner": "DOWN",
      "mode": "paper"
    },
    {
      "market": 166,
      "strategy": "ANCHOR",
      "side": "UP",
      "entry": 0.57,
      "result": "loss",
      "net_pnl": -1.02,
      "slip_pnl": -1.02,
      "winner": "DOWN",
      "mode": "paper"
    },
    {
      "market": 166,
      "strategy": "SQUEEZE",
      "side": "DOWN",
      "entry": 0.62,
      "result": "win",
      "net_pnl": 0.5929,
      "slip_pnl": 0.5185,
      "winner": "DOWN",
      "mode": "paper"
    },
    {
      "market": 166,
      "strategy": "P1L",
      "side": "DOWN",
      "entry": 0.455,
      "result": "win",
      "net_pnl": 1.1778,
      "slip_pnl": 1.0419,
      "winner": "DOWN",
      "mode": "paper"
    },
    {
      "market": 166,
      "strategy": "DRIFT",
      "side": "UP",
      "entry": 0.54,
      "result": "loss",
      "net_pnl": -1.02,
      "slip_pnl": -1.02,
      "winner": "DOWN",
      "mode": "paper"
    },
    {
      "market": 166,
      "strategy": "SQUEEZE",
      "side": "DOWN",
      "entry": 0.83,
      "result": "win",
      "net_pnl": 0.1848,
      "slip_pnl": 0.1428,
      "winner": "DOWN",
      "mode": "paper"
    },
    {
      "market": 166,
      "strategy": "FADE",
      "side": "UP",
      "entry": 0.16,
      "result": "loss",
      "net_pnl": -1.02,
      "slip_pnl": -1.02,
      "winner": "DOWN",
      "mode": "paper"
    },
    {
      "market": 166,
      "strategy": "P1L",
      "side": "UP",
      "entry": 0.48,
      "result": "pending",
      "net_pnl": null,
      "slip_pnl": null,
      "winner": "",
      "mode": "paper"
    },
    {
      "market": 166,
      "strategy": "DRIFT",
      "side": "UP",
      "entry": 0.34,
      "result": "pending",
      "net_pnl": null,
      "slip_pnl": null,
      "winner": "",
      "mode": "paper"
    },
    {
      "market": 166,
      "strategy": "SQUEEZE",
      "side": "UP",
      "entry": 0.37,
      "result": "pending",
      "net_pnl": null,
      "slip_pnl": null,
      "winner": "",
      "mode": "paper"
    },
    {
      "market": 166,
      "strategy": "FADE",
      "side": "UP",
      "entry": 0.34,
      "result": "pending",
      "net_pnl": null,
      "slip_pnl": null,
      "winner": "",
      "mode": "paper"
    },
    {
      "market": 166,
      "strategy": "ANCHOR",
      "side": "DOWN",
      "entry": 0.65,
      "result": "pending",
      "net_pnl": null,
      "slip_pnl": null,
      "winner": "",
      "mode": "paper"
    },
    {
      "market": 166,
      "strategy": "P2A",
      "side": "DOWN",
      "entry": 0.88,
      "result": "pending",
      "net_pnl": null,
      "slip_pnl": null,
      "winner": "",
      "mode": "paper"
    },
    {
      "market": 166,
      "strategy": "P1L",
      "side": "DOWN",
      "entry": 0.475,
      "result": "pending",
      "net_pnl": null,
      "slip_pnl": null,
      "winner": "",
      "mode": "paper"
    },
    {
      "market": 166,
      "strategy": "DRIFT",
      "side": "DOWN",
      "entry": 0.54,
      "result": "pending",
      "net_pnl": null,
      "slip_pnl": null,
      "winner": "",
      "mode": "paper"
    }
  ]
}