{
  "last_updated": "2026-03-30 15:29:55 UTC",
  "summary": {
    "total_pnl": 23.7,
    "markets_traded": 137,
    "wins": 98,
    "losses": 37,
    "win_rate": 71.5,
    "best_trade": 6.4,
    "worst_trade": -8.55,
    "daily_stop_loss_hit": false,
    "mode": "paper"
  },
  "trades": [
    {
      "market": 186,
      "time": "2026-03-30 15:25:00 UTC",
      "phases": "Phase 1 + Phase 2 + Phase 3",
      "outcome": "P1: no trigger | P2: buy(s) filled \u2014 stop loss exit | P3: snipe win @ $0.9900",
      "pnl": -2.5,
      "mode": "paper",
      "running_pnl": 23.7
    },
    {
      "market": 185,
      "time": "2026-03-30 15:20:00 UTC",
      "phases": "Phase 1 + Phase 2 + Phase 3",
      "outcome": "P1: no trigger | P2: round trip complete | P3: snipe win @ $0.9900",
      "pnl": 0.85,
      "mode": "paper",
      "running_pnl": 26.2
    },
    {
      "market": 184,
      "time": "2026-03-30 15:15:00 UTC",
      "phases": "Phase 1 + Phase 2 + Phase 3",
      "outcome": "P1: no trigger | P2: round trip complete | P3: snipe win @ $0.9900",
      "pnl": 1.11,
      "mode": "paper",
      "running_pnl": 25.35
    },
    {
      "market": 183,
      "time": "2026-03-30 15:10:00 UTC",
      "phases": "Phase 1 + Phase 2 + Phase 3",
      "outcome": "P1: no trigger | P2: round trip complete | P3: snipe loss @ $0.0150",
      "pnl": -4.25,
      "mode": "paper",
      "running_pnl": 24.24
    },
    {
      "market": 182,
      "time": "2026-03-30 15:05:00 UTC",
      "phases": "Phase 1 + Phase 2 + Phase 3",
      "outcome": "P1: directional win @ $0.9900 | P2: skipped \u2014 DOWN mid 0.4600 out of range | P3: snipe win @ $0.9900",
      "pnl": 6.28,
      "mode": "paper",
      "running_pnl": 28.49
    },
    {
      "market": 181,
      "time": "2026-03-30 15:00:00 UTC",
      "phases": "Phase 1 + Phase 2 + Phase 3",
      "outcome": "P1: directional loss @ $0.0100 | P2: skipped \u2014 UP mid 0.4550 out of range | P3: snipe win @ $0.9900",
      "pnl": -4.37,
      "mode": "paper",
      "running_pnl": 22.21
    },
    {
      "market": 180,
      "time": "2026-03-30 14:55:00 UTC",
      "phases": "Phase 1 + Phase 2 + Phase 3",
      "outcome": "P1: no trigger | P2: round trip complete | P3: snipe win @ $0.9900",
      "pnl": 1.14,
      "mode": "paper",
      "running_pnl": 26.58
    },
    {
      "market": 179,
      "time": "2026-03-30 14:50:00 UTC",
      "phases": "Phase 1 + Phase 2 + Phase 3",
      "outcome": "P1: no trigger | P2: round trip complete | P3: snipe win @ $0.9900",
      "pnl": 1.17,
      "mode": "paper",
      "running_pnl": 25.44
    },
    {
      "market": 178,
      "time": "2026-03-30 14:45:00 UTC",
      "phases": "Phase 1 + Phase 2 + Phase 3",
      "outcome": "P1: no trigger | P2: skipped \u2014 UP mid 0.5650 out of range | P3: snipe win @ $0.9900",
      "pnl": 0.42,
      "mode": "paper",
      "running_pnl": 24.27
    },
    {
      "market": 177,
      "time": "2026-03-30 14:40:00 UTC",
      "phases": "Phase 1 + Phase 2 + Phase 3",
      "outcome": "P1: no trigger | P2: round trip complete | P3: snipe win @ $0.9900",
      "pnl": 1.14,
      "mode": "paper",
      "running_pnl": 23.85
    },
    {
      "market": 176,
      "time": "2026-03-30 14:35:00 UTC",
      "phases": "Phase 1 + Phase 2 + Phase 3",
      "outcome": "P1: directional loss @ $0.0100 | P2: skipped \u2014 UP mid 0.5800 out of range | P3: snipe win @ $0.9900",
      "pnl": -4.42,
      "mode": "paper",
      "running_pnl": 22.71
    },
    {
      "market": 175,
      "time": "2026-03-30 14:30:00 UTC",
      "phases": "Phase 1 + Phase 2 + Phase 3",
      "outcome": "P1: no trigger | P2: buy(s) filled \u2014 stop loss exit | P3: snipe win @ $0.9900",
      "pnl": -2.5,
      "mode": "paper",
      "running_pnl": 27.14
    },
    {
      "market": 174,
      "time": "2026-03-30 14:25:00 UTC",
      "phases": "Phase 1 + Phase 2 + Phase 3",
      "outcome": "P1: directional win @ $0.9900 | P2: skipped \u2014 UP mid 0.5450 out of range | P3: snipe win @ $0.9900",
      "pnl": 6.4,
      "mode": "paper",
      "running_pnl": 29.64
    },
    {
      "market": 173,
      "time": "2026-03-30 14:20:00 UTC",
      "phases": "Phase 1 + Phase 2 + Phase 3",
      "outcome": "P1: directional win @ $0.9900 | P2: skipped \u2014 UP mid 0.5900 out of range | P3: snipe win @ $0.9900",
      "pnl": 3.88,
      "mode": "paper",
      "running_pnl": 23.24
    },
    {
      "market": 172,
      "time": "2026-03-30 14:15:00 UTC",
      "phases": "Phase 1 + Phase 2 + Phase 3",
      "outcome": "P1: directional loss @ $0.0100 | P2: skipped \u2014 UP mid 0.5850 out of range | P3: snipe win @ $0.9900",
      "pnl": -4.39,
      "mode": "paper",
      "running_pnl": 19.36
    },
    {
      "market": 171,
      "time": "2026-03-30 14:10:00 UTC",
      "phases": "Phase 1 + Phase 2 + Phase 3",
      "outcome": "P1: directional loss @ $0.0100 | P2: skipped \u2014 UP mid 0.5450 out of range | P3: snipe win @ $0.9900",
      "pnl": -4.58,
      "mode": "paper",
      "running_pnl": 23.75
    },
    {
      "market": 170,
      "time": "2026-03-30 14:05:00 UTC",
      "phases": "Phase 1 + Phase 2 + Phase 3",
      "outcome": "P1: no trigger | P2: round trip complete | P3: snipe loss @ $0.2050",
      "pnl": -3.21,
      "mode": "paper",
      "running_pnl": 28.33
    },
    {
      "market": 169,
      "time": "2026-03-30 14:00:00 UTC",
      "phases": "Phase 1 + Phase 2 + Phase 3",
      "outcome": "P1: no trigger | P2: skipped \u2014 UP mid 0.5700 out of range | P3: snipe win @ $0.9900",
      "pnl": 0.48,
      "mode": "paper",
      "running_pnl": 31.54
    },
    {
      "market": 168,
      "time": "2026-03-30 13:55:00 UTC",
      "phases": "Phase 1 + Phase 2 + Phase 3",
      "outcome": "P1: no trigger | P2: skipped \u2014 UP mid 0.4250 out of range | P3: snipe win @ $0.9900",
      "pnl": 0.51,
      "mode": "paper",
      "running_pnl": 31.06
    },
    {
      "market": 167,
      "time": "2026-03-30 13:50:00 UTC",
      "phases": "Phase 1 + Phase 2 + Phase 3",
      "outcome": "P1: no trigger | P2: skipped \u2014 UP mid 0.5750 out of range | P3: snipe win @ $0.9900",
      "pnl": 0.48,
      "mode": "paper",
      "running_pnl": 30.55
    },
    {
      "market": 166,
      "time": "2026-03-30 13:45:00 UTC",
      "phases": "Phase 1 + Phase 2 + Phase 3",
      "outcome": "P1: directional loss @ $0.0100 | P2: skipped \u2014 UP mid 0.6550 out of range | P3: snipe win @ $0.9900",
      "pnl": -4.4,
      "mode": "paper",
      "running_pnl": 30.07
    },
    {
      "market": 165,
      "time": "2026-03-30 13:40:00 UTC",
      "phases": "Phase 1 + Phase 2 + Phase 3",
      "outcome": "P1: directional win @ $0.9900 | P2: skipped \u2014 UP mid 0.4200 out of range | P3: snipe win @ $0.9900",
      "pnl": 4.02,
      "mode": "paper",
      "running_pnl": 34.47
    },
    {
      "market": 164,
      "time": "2026-03-30 13:35:00 UTC",
      "phases": "Phase 1 + Phase 2 + Phase 3",
      "outcome": "P1: no trigger | P2: round trip complete | P3: snipe loss @ $0.0350",
      "pnl": -4.14,
      "mode": "paper",
      "running_pnl": 30.45
    },
    {
      "market": 163,
      "time": "2026-03-30 13:30:00 UTC",
      "phases": "Phase 1 + Phase 2 + Phase 3",
      "outcome": "P1: directional loss @ $0.0100 | P2: skipped \u2014 UP mid 0.3600 out of range | P3: snipe win @ $0.9900",
      "pnl": -4.46,
      "mode": "paper",
      "running_pnl": 34.59
    },
    {
      "market": 162,
      "time": "2026-03-30 13:25:00 UTC",
      "phases": "Phase 1 + Phase 2 + Phase 3",
      "outcome": "P1: directional win @ $0.9900 | P2: skipped \u2014 UP mid 0.3550 out of range | P3: snipe win @ $0.9900",
      "pnl": 3.16,
      "mode": "paper",
      "running_pnl": 39.05
    },
    {
      "market": 161,
      "time": "2026-03-30 13:20:00 UTC",
      "phases": "Phase 1 + Phase 2 + Phase 3",
      "outcome": "P1: no trigger | P2: round trip complete | P3: snipe win @ $0.9900",
      "pnl": 1.02,
      "mode": "paper",
      "running_pnl": 35.89
    },
    {
      "market": 160,
      "time": "2026-03-30 13:15:00 UTC",
      "phases": "Phase 1 + Phase 2 + Phase 3",
      "outcome": "P1: no trigger | P2: round trip complete | P3: snipe win @ $0.9900",
      "pnl": 1.17,
      "mode": "paper",
      "running_pnl": 34.87
    },
    {
      "market": 159,
      "time": "2026-03-30 13:10:00 UTC",
      "phases": "Phase 1 + Phase 2 + Phase 3",
      "outcome": "P1: directional loss @ $0.0100 | P2: skipped \u2014 UP mid 0.4150 out of range | P3: snipe win @ $0.9900",
      "pnl": -4.42,
      "mode": "paper",
      "running_pnl": 33.7
    },
    {
      "market": 158,
      "time": "2026-03-30 13:05:00 UTC",
      "phases": "Phase 1 + Phase 2 + Phase 3",
      "outcome": "P1: no trigger | P2: round trip complete | P3: snipe win @ $0.9900",
      "pnl": 1.14,
      "mode": "paper",
      "running_pnl": 38.12
    },
    {
      "market": 157,
      "time": "2026-03-30 13:00:00 UTC",
      "phases": "Phase 1 + Phase 2 + Phase 3",
      "outcome": "P1: directional win @ $0.9900 | P2: skipped \u2014 UP mid 0.4500 out of range | P3: snipe loss @ $0.0700",
      "pnl": 1.41,
      "mode": "paper",
      "running_pnl": 36.98
    },
    {
      "market": 156,
      "time": "2026-03-30 12:55:00 UTC",
      "phases": "Phase 1 + Phase 2 + Phase 3",
      "outcome": "P1: directional win @ $0.9900 | P2: skipped \u2014 UP mid 0.4600 out of range | P3: snipe win @ $0.9900",
      "pnl": 6.28,
      "mode": "paper",
      "running_pnl": 35.58
    },
    {
      "market": 155,
      "time": "2026-03-30 12:50:00 UTC",
      "phases": "Phase 1 + Phase 2 + Phase 3",
      "outcome": "P1: no trigger | P2: round trip complete | P3: snipe win @ $0.9450",
      "pnl": 0.89,
      "mode": "paper",
      "running_pnl": 29.3
    },
    {
      "market": 154,
      "time": "2026-03-30 12:45:00 UTC",
      "phases": "Phase 1 + Phase 2 + Phase 3",
      "outcome": "P1: no trigger | P2: round trip complete | P3: snipe loss @ $0.0250",
      "pnl": -4.2,
      "mode": "paper",
      "running_pnl": 28.41
    },
    {
      "market": 153,
      "time": "2026-03-30 12:40:00 UTC",
      "phases": "Phase 1 + Phase 2 + Phase 3",
      "outcome": "P1: directional win @ $0.9900 | P2: skipped \u2014 UP mid 0.4500 out of range | P3: snipe loss @ $0.0250",
      "pnl": 1.16,
      "mode": "paper",
      "running_pnl": 32.6
    },
    {
      "market": 152,
      "time": "2026-03-30 12:35:00 UTC",
      "phases": "Phase 1 + Phase 2 + Phase 3",
      "outcome": "P1: no trigger | P2: round trip complete | P3: snipe win @ $0.9900",
      "pnl": 1.17,
      "mode": "paper",
      "running_pnl": 31.44
    },
    {
      "market": 151,
      "time": "2026-03-30 12:30:00 UTC",
      "phases": "Phase 1 + Phase 2 + Phase 3",
      "outcome": "P1: directional win @ $0.9900 | P2: skipped \u2014 UP mid 0.4600 out of range | P3: snipe win @ $0.9900",
      "pnl": 6.25,
      "mode": "paper",
      "running_pnl": 30.27
    },
    {
      "market": 150,
      "time": "2026-03-30 12:25:00 UTC",
      "phases": "Phase 1 + Phase 2 + Phase 3",
      "outcome": "P1: no trigger | P2: skipped \u2014 UP mid 0.4250 out of range | P3: snipe win @ $0.9900",
      "pnl": 0.45,
      "mode": "paper",
      "running_pnl": 24.02
    },
    {
      "market": 149,
      "time": "2026-03-30 12:20:00 UTC",
      "phases": "Phase 1 + Phase 2 + Phase 3",
      "outcome": "P1: directional loss @ $0.0100 | P2: skipped \u2014 UP mid 0.4150 out of range | P3: snipe loss @ $0.3200",
      "pnl": -8.15,
      "mode": "paper",
      "running_pnl": 23.57
    },
    {
      "market": 148,
      "time": "2026-03-30 12:15:00 UTC",
      "phases": "Phase 1 + Phase 2 + Phase 3",
      "outcome": "P1: directional loss @ $0.0100 | P2: skipped \u2014 UP mid 0.4050 out of range | P3: snipe win @ $0.9900",
      "pnl": -4.4,
      "mode": "paper",
      "running_pnl": 31.72
    },
    {
      "market": 147,
      "time": "2026-03-30 12:10:00 UTC",
      "phases": "Phase 1 + Phase 2 + Phase 3",
      "outcome": "P1: no trigger | P2: skipped \u2014 UP mid 0.4250 out of range | P3: snipe win @ $0.9900",
      "pnl": 0.51,
      "mode": "paper",
      "running_pnl": 36.12
    },
    {
      "market": 146,
      "time": "2026-03-30 12:05:00 UTC",
      "phases": "Phase 1 + Phase 2 + Phase 3",
      "outcome": "P1: directional loss @ $0.0100 | P2: skipped \u2014 UP mid 0.4150 out of range | P3: snipe win @ $0.9900",
      "pnl": -4.42,
      "mode": "paper",
      "running_pnl": 35.61
    },
    {
      "market": 145,
      "time": "2026-03-30 12:00:00 UTC",
      "phases": "Phase 1 + Phase 2 + Phase 3",
      "outcome": "P1: no trigger | P2: skipped \u2014 UP mid 0.5600 out of range | P3: snipe win @ $0.9900",
      "pnl": 0.51,
      "mode": "paper",
      "running_pnl": 40.03
    },
    {
      "market": 144,
      "time": "2026-03-30 11:55:00 UTC",
      "phases": "Phase 1 + Phase 2 + Phase 3",
      "outcome": "P1: no trigger | P2: buy(s) filled \u2014 stop loss exit | P3: snipe win @ $0.9900",
      "pnl": -1.6,
      "mode": "paper",
      "running_pnl": 39.52
    },
    {
      "market": 143,
      "time": "2026-03-30 11:50:00 UTC",
      "phases": "Phase 1 + Phase 2 + Phase 3",
      "outcome": "P1: directional loss @ $0.0100 | P2: skipped \u2014 UP mid 0.4550 out of range | P3: snipe win @ $0.9900",
      "pnl": -4.37,
      "mode": "paper",
      "running_pnl": 41.12
    },
    {
      "market": 142,
      "time": "2026-03-30 11:45:00 UTC",
      "phases": "Phase 1 + Phase 2 + Phase 3",
      "outcome": "P1: no trigger | P2: round trip complete | P3: snipe win @ $0.9900",
      "pnl": 1.08,
      "mode": "paper",
      "running_pnl": 45.49
    },
    {
      "market": 141,
      "time": "2026-03-30 11:40:00 UTC",
      "phases": "Phase 1 + Phase 2 + Phase 3",
      "outcome": "P1: no trigger | P2: round trip complete | P3: snipe win @ $0.9900",
      "pnl": 1.14,
      "mode": "paper",
      "running_pnl": 44.41
    },
    {
      "market": 140,
      "time": "2026-03-30 11:35:00 UTC",
      "phases": "Phase 1 + Phase 2 + Phase 3",
      "outcome": "P1: no trigger | P2: skipped \u2014 UP mid 0.5600 out of range | P3: snipe win @ $0.9900",
      "pnl": 0.48,
      "mode": "paper",
      "running_pnl": 43.28
    },
    {
      "market": 139,
      "time": "2026-03-30 11:30:00 UTC",
      "phases": "Phase 1 + Phase 2 + Phase 3",
      "outcome": "P1: no trigger | P2: round trip complete | P3: snipe win @ $0.9900",
      "pnl": 1.14,
      "mode": "paper",
      "running_pnl": 42.8
    },
    {
      "market": 138,
      "time": "2026-03-30 11:25:00 UTC",
      "phases": "Phase 1 + Phase 2 + Phase 3",
      "outcome": "P1: directional loss @ $0.0100 | P2: skipped \u2014 UP mid 0.3850 out of range | P3: snipe win @ $0.9900",
      "pnl": -4.43,
      "mode": "paper",
      "running_pnl": 41.66
    },
    {
      "market": 137,
      "time": "2026-03-30 11:20:00 UTC",
      "phases": "Phase 1 + Phase 2 + Phase 3",
      "outcome": "P1: no trigger | P2: round trip complete | P3: snipe win @ $0.9900",
      "pnl": 1.14,
      "mode": "paper",
      "running_pnl": 46.09
    },
    {
      "market": 136,
      "time": "2026-03-30 11:15:00 UTC",
      "phases": "Phase 1 + Phase 2 + Phase 3",
      "outcome": "P1: no trigger | P2: skipped \u2014 UP mid 0.4350 out of range | P3: snipe win @ $0.9900",
      "pnl": 0.48,
      "mode": "paper",
      "running_pnl": 44.95
    },
    {
      "market": 135,
      "time": "2026-03-30 11:10:00 UTC",
      "phases": "Phase 1 + Phase 2 + Phase 3",
      "outcome": "P1: no trigger | P2: skipped \u2014 UP mid 0.4450 out of range | P3: snipe win @ $0.9900",
      "pnl": 0.51,
      "mode": "paper",
      "running_pnl": 44.47
    },
    {
      "market": 134,
      "time": "2026-03-30 11:05:00 UTC",
      "phases": "Phase 1 + Phase 2 + Phase 3",
      "outcome": "P1: no trigger | P2: round trip complete | P3: snipe win @ $0.9900",
      "pnl": 1.1,
      "mode": "paper",
      "running_pnl": 43.96
    },
    {
      "market": 133,
      "time": "2026-03-30 11:00:00 UTC",
      "phases": "Phase 1 + Phase 2 + Phase 3",
      "outcome": "P1: no trigger | P2: round trip complete | P3: snipe win @ $0.9900",
      "pnl": 1.14,
      "mode": "paper",
      "running_pnl": 42.86
    },
    {
      "market": 132,
      "time": "2026-03-30 10:55:00 UTC",
      "phases": "Phase 1 + Phase 2 + Phase 3",
      "outcome": "P1: no trigger | P2: round trip complete | P3: snipe win @ $0.8050",
      "pnl": 0.12,
      "mode": "paper",
      "running_pnl": 41.72
    },
    {
      "market": 131,
      "time": "2026-03-30 10:50:00 UTC",
      "phases": "Phase 1 + Phase 2 + Phase 3",
      "outcome": "P1: no trigger | P2: round trip complete | P3: snipe win @ $0.9900",
      "pnl": 1.17,
      "mode": "paper",
      "running_pnl": 41.6
    },
    {
      "market": 130,
      "time": "2026-03-30 10:45:00 UTC",
      "phases": "Phase 1 + Phase 2 + Phase 3",
      "outcome": "P1: no trigger | P2: round trip complete | P3: snipe win @ $0.9900",
      "pnl": 1.17,
      "mode": "paper",
      "running_pnl": 40.43
    },
    {
      "market": 129,
      "time": "2026-03-30 10:40:00 UTC",
      "phases": "Phase 1 + Phase 2 + Phase 3",
      "outcome": "P1: no trigger | P2: round trip complete | P3: snipe win @ $0.9900",
      "pnl": 1.02,
      "mode": "paper",
      "running_pnl": 39.27
    },
    {
      "market": 128,
      "time": "2026-03-30 10:35:00 UTC",
      "phases": "Phase 1 + Phase 2 + Phase 3",
      "outcome": "P1: no trigger | P2: round trip complete | P3: snipe win @ $0.9900",
      "pnl": 1.14,
      "mode": "paper",
      "running_pnl": 38.25
    },
    {
      "market": 127,
      "time": "2026-03-30 10:30:00 UTC",
      "phases": "Phase 1 + Phase 2 + Phase 3",
      "outcome": "P1: no trigger | P2: round trip complete | P3: snipe win @ $0.9900",
      "pnl": 1.14,
      "mode": "paper",
      "running_pnl": 37.11
    },
    {
      "market": 126,
      "time": "2026-03-30 10:25:00 UTC",
      "phases": "Phase 1 + Phase 2 + Phase 3",
      "outcome": "P1: no trigger | P2: skipped \u2014 UP mid 0.4350 out of range | P3: snipe win @ $0.9900",
      "pnl": 0.48,
      "mode": "paper",
      "running_pnl": 35.97
    },
    {
      "market": 125,
      "time": "2026-03-30 10:20:00 UTC",
      "phases": "Phase 1 + Phase 2 + Phase 3",
      "outcome": "P1: no trigger | P2: round trip complete | P3: snipe win @ $0.9900",
      "pnl": 1.17,
      "mode": "paper",
      "running_pnl": 35.49
    },
    {
      "market": 124,
      "time": "2026-03-30 10:15:00 UTC",
      "phases": "Phase 1 + Phase 2 + Phase 3",
      "outcome": "P1: no trigger | P2: skipped \u2014 UP mid 0.5700 out of range | P3: snipe win @ $0.9900",
      "pnl": 0.51,
      "mode": "paper",
      "running_pnl": 34.32
    },
    {
      "market": 123,
      "time": "2026-03-30 10:10:00 UTC",
      "phases": "Phase 1 + Phase 2 + Phase 3",
      "outcome": "P1: no trigger | P2: skipped \u2014 UP mid 0.5750 out of range | P3: snipe win @ $0.9900",
      "pnl": 0.42,
      "mode": "paper",
      "running_pnl": 33.81
    },
    {
      "market": 122,
      "time": "2026-03-30 10:05:00 UTC",
      "phases": "Phase 1 + Phase 2 + Phase 3",
      "outcome": "P1: no trigger | P2: round trip complete | P3: snipe win @ $0.9900",
      "pnl": 1.02,
      "mode": "paper",
      "running_pnl": 33.39
    },
    {
      "market": 121,
      "time": "2026-03-30 10:00:00 UTC",
      "phases": "Phase 1 + Phase 2 + Phase 3",
      "outcome": "P1: directional loss @ $0.0100 | P2: skipped \u2014 UP mid 0.5950 out of range | P3: snipe win @ $0.9900",
      "pnl": -4.4,
      "mode": "paper",
      "running_pnl": 32.37
    },
    {
      "market": 120,
      "time": "2026-03-30 09:55:00 UTC",
      "phases": "Phase 1 + Phase 2 + Phase 3",
      "outcome": "P1: no trigger | P2: skipped \u2014 UP mid 0.4350 out of range | P3: snipe win @ $0.9900",
      "pnl": 0.51,
      "mode": "paper",
      "running_pnl": 36.77
    },
    {
      "market": 119,
      "time": "2026-03-30 09:50:00 UTC",
      "phases": "Phase 1 + Phase 2 + Phase 3",
      "outcome": "P1: no trigger | P2: skipped \u2014 UP mid 0.4450 out of range | P3: snipe win @ $0.9900",
      "pnl": 0.51,
      "mode": "paper",
      "running_pnl": 36.26
    },
    {
      "market": 118,
      "time": "2026-03-30 09:45:00 UTC",
      "phases": "Phase 1 + Phase 2 + Phase 3",
      "outcome": "P1: no trigger | P2: round trip complete | P3: snipe win @ $0.9900",
      "pnl": 1.17,
      "mode": "paper",
      "running_pnl": 35.75
    },
    {
      "market": 117,
      "time": "2026-03-30 09:40:00 UTC",
      "phases": "Phase 1 + Phase 2 + Phase 3",
      "outcome": "P1: directional loss @ $0.0100 | P2: skipped \u2014 UP mid 0.5450 out of range | P3: snipe win @ $0.9900",
      "pnl": -4.46,
      "mode": "paper",
      "running_pnl": 34.58
    },
    {
      "market": 116,
      "time": "2026-03-30 09:35:00 UTC",
      "phases": "Phase 1 + Phase 2 + Phase 3",
      "outcome": "P1: no trigger | P2: round trip complete | P3: snipe win @ $0.9900",
      "pnl": 1.17,
      "mode": "paper",
      "running_pnl": 39.04
    },
    {
      "market": 115,
      "time": "2026-03-30 09:30:00 UTC",
      "phases": "Phase 1 + Phase 2 + Phase 3",
      "outcome": "P1: no trigger | P2: skipped \u2014 UP mid 0.5550 out of range | P3: snipe win @ $0.9900",
      "pnl": 0.51,
      "mode": "paper",
      "running_pnl": 37.87
    },
    {
      "market": 114,
      "time": "2026-03-30 09:25:00 UTC",
      "phases": "Phase 1 + Phase 2 + Phase 3",
      "outcome": "P1: no trigger | P2: round trip complete | P3: snipe win @ $0.9900",
      "pnl": 1.08,
      "mode": "paper",
      "running_pnl": 37.36
    },
    {
      "market": 113,
      "time": "2026-03-30 09:20:00 UTC",
      "phases": "Phase 1 + Phase 2 + Phase 3",
      "outcome": "P1: directional win @ $0.9900 | P2: skipped \u2014 UP mid 0.5450 out of range | P3: snipe win @ $0.9900",
      "pnl": 6.31,
      "mode": "paper",
      "running_pnl": 36.28
    },
    {
      "market": 112,
      "time": "2026-03-30 09:15:00 UTC",
      "phases": "Phase 1 + Phase 2 + Phase 3",
      "outcome": "P1: no trigger | P2: round trip complete | P3: snipe win @ $0.9900",
      "pnl": 1.14,
      "mode": "paper",
      "running_pnl": 29.98
    },
    {
      "market": 111,
      "time": "2026-03-30 09:10:00 UTC",
      "phases": "Phase 1 + Phase 2 + Phase 3",
      "outcome": "P1: no trigger | P2: buy(s) filled \u2014 stop loss exit | P3: snipe loss @ $0.0100",
      "pnl": -8.55,
      "mode": "paper",
      "running_pnl": 28.84
    },
    {
      "market": 110,
      "time": "2026-03-30 09:05:00 UTC",
      "phases": "Phase 1 + Phase 2 + Phase 3",
      "outcome": "P1: no trigger | P2: buy(s) filled \u2014 stop loss exit | P3: snipe win @ $0.9900",
      "pnl": -1.54,
      "mode": "paper",
      "running_pnl": 37.39
    },
    {
      "market": 109,
      "time": "2026-03-30 09:00:00 UTC",
      "phases": "Phase 1 + Phase 2 + Phase 3",
      "outcome": "P1: directional win @ $0.9900 | P2: skipped \u2014 UP mid 0.3950 out of range | P3: snipe win @ $0.9900",
      "pnl": 3.64,
      "mode": "paper",
      "running_pnl": 38.93
    },
    {
      "market": 108,
      "time": "2026-03-30 08:55:00 UTC",
      "phases": "Phase 1 + Phase 2 + Phase 3",
      "outcome": "P1: no trigger | P2: no fills | P3: snipe win @ $0.9900",
      "pnl": 0.48,
      "mode": "paper",
      "running_pnl": 35.29
    },
    {
      "market": 107,
      "time": "2026-03-30 08:50:00 UTC",
      "phases": "Phase 1 + Phase 2 + Phase 3",
      "outcome": "P1: no trigger | P2: buy(s) filled \u2014 stop loss exit | P3: snipe win @ $0.9900",
      "pnl": -1.83,
      "mode": "paper",
      "running_pnl": 34.81
    },
    {
      "market": 106,
      "time": "2026-03-30 08:45:00 UTC",
      "phases": "Phase 1 + Phase 2 + Phase 3",
      "outcome": "P1: no trigger | P2: round trip complete | P3: snipe win @ $0.9900",
      "pnl": 1.14,
      "mode": "paper",
      "running_pnl": 36.64
    },
    {
      "market": 105,
      "time": "2026-03-30 08:40:00 UTC",
      "phases": "Phase 1 + Phase 2 + Phase 3",
      "outcome": "P1: no trigger | P2: round trip complete | P3: snipe win @ $0.9900",
      "pnl": 1.17,
      "mode": "paper",
      "running_pnl": 35.5
    },
    {
      "market": 104,
      "time": "2026-03-30 08:35:00 UTC",
      "phases": "Phase 1 + Phase 2 + Phase 3",
      "outcome": "P1: directional loss @ $0.0100 | P2: skipped \u2014 UP mid 0.3700 out of range | P3: snipe win @ $0.9900",
      "pnl": -4.49,
      "mode": "paper",
      "running_pnl": 34.33
    },
    {
      "market": 103,
      "time": "2026-03-30 08:30:00 UTC",
      "phases": "Phase 1 + Phase 2 + Phase 3",
      "outcome": "P1: directional win @ $0.9900 | P2: skipped \u2014 UP mid 0.3950 out of range | P3: snipe win @ $0.9300",
      "pnl": 3.31,
      "mode": "paper",
      "running_pnl": 38.83
    },
    {
      "market": 102,
      "time": "2026-03-30 08:25:00 UTC",
      "phases": "Phase 1 + Phase 2 + Phase 3",
      "outcome": "P1: no trigger | P2: skipped \u2014 UP mid 0.4250 out of range | P3: snipe win @ $0.9900",
      "pnl": 0.48,
      "mode": "paper",
      "running_pnl": 35.51
    },
    {
      "market": 101,
      "time": "2026-03-30 08:20:00 UTC",
      "phases": "Phase 1 + Phase 2 + Phase 3",
      "outcome": "P1: no trigger | P2: skipped \u2014 UP mid 0.4450 out of range | P3: snipe win @ $0.9900",
      "pnl": 0.51,
      "mode": "paper",
      "running_pnl": 35.03
    },
    {
      "market": 100,
      "time": "2026-03-30 08:15:00 UTC",
      "phases": "Phase 1 + Phase 2 + Phase 3",
      "outcome": "P1: no trigger | P2: round trip complete | P3: snipe win @ $0.9900",
      "pnl": 1.17,
      "mode": "paper",
      "running_pnl": 34.52
    },
    {
      "market": 99,
      "time": "2026-03-30 08:10:00 UTC",
      "phases": "Phase 1 + Phase 2 + Phase 3",
      "outcome": "P1: directional loss @ $0.0100 | P2: skipped \u2014 UP mid 0.4050 out of range | P3: snipe win @ $0.9900",
      "pnl": -4.57,
      "mode": "paper",
      "running_pnl": 33.36
    },
    {
      "market": 98,
      "time": "2026-03-30 08:05:00 UTC",
      "phases": "Phase 1 + Phase 2 + Phase 3",
      "outcome": "P1: no trigger | P2: round trip complete | P3: snipe win @ $0.9350",
      "pnl": 0.83,
      "mode": "paper",
      "running_pnl": 37.93
    },
    {
      "market": 97,
      "time": "2026-03-30 08:00:00 UTC",
      "phases": "Phase 1 + Phase 2 + Phase 3",
      "outcome": "P1: no trigger | P2: skipped \u2014 UP mid 0.5550 out of range | P3: snipe win @ $0.9900",
      "pnl": 0.51,
      "mode": "paper",
      "running_pnl": 37.09
    },
    {
      "market": 96,
      "time": "2026-03-30 07:55:00 UTC",
      "phases": "Phase 1 + Phase 2 + Phase 3",
      "outcome": "P1: no trigger | P2: skipped \u2014 UP mid 0.5750 out of range | P3: snipe win @ $0.9900",
      "pnl": 0.51,
      "mode": "paper",
      "running_pnl": 36.58
    },
    {
      "market": 95,
      "time": "2026-03-30 07:50:00 UTC",
      "phases": "Phase 1 + Phase 2 + Phase 3",
      "outcome": "P1: directional win @ $0.9900 | P2: skipped \u2014 UP mid 0.6150 out of range | P3: snipe win @ $0.9900",
      "pnl": 3.57,
      "mode": "paper",
      "running_pnl": 36.07
    },
    {
      "market": 94,
      "time": "2026-03-30 07:45:00 UTC",
      "phases": "Phase 1 + Phase 2 + Phase 3",
      "outcome": "P1: directional win @ $0.9900 | P2: skipped \u2014 UP mid 0.6200 out of range | P3: snipe win @ $0.9900",
      "pnl": 3.5,
      "mode": "paper",
      "running_pnl": 32.51
    },
    {
      "market": 93,
      "time": "2026-03-30 07:40:00 UTC",
      "phases": "Phase 1 + Phase 2 + Phase 3",
      "outcome": "P1: no trigger | P2: buy(s) filled \u2014 stop loss exit | P3: no snipe opportunity",
      "pnl": -2.02,
      "mode": "paper",
      "running_pnl": 29.0
    },
    {
      "market": 92,
      "time": "2026-03-30 07:35:00 UTC",
      "phases": "Phase 1 + Phase 2 + Phase 3",
      "outcome": "P1: directional win @ $0.9900 | P2: skipped \u2014 UP mid 0.5450 out of range | P3: snipe win @ $0.9900",
      "pnl": 6.37,
      "mode": "paper",
      "running_pnl": 31.02
    },
    {
      "market": 91,
      "time": "2026-03-30 07:30:00 UTC",
      "phases": "Phase 1 + Phase 2 + Phase 3",
      "outcome": "P1: directional loss @ $0.0100 | P2: skipped \u2014 UP mid 0.5450 out of range | P3: snipe win @ $0.7100",
      "pnl": -5.95,
      "mode": "paper",
      "running_pnl": 24.65
    },
    {
      "market": 90,
      "time": "2026-03-30 07:25:00 UTC",
      "phases": "Phase 1 + Phase 2 + Phase 3",
      "outcome": "P1: no trigger | P2: round trip complete | P3: snipe win @ $0.9900",
      "pnl": 1.14,
      "mode": "paper",
      "running_pnl": 30.6
    },
    {
      "market": 89,
      "time": "2026-03-30 07:20:00 UTC",
      "phases": "Phase 1 + Phase 2 + Phase 3",
      "outcome": "P1: no trigger | P2: round trip complete | P3: snipe win @ $0.9900",
      "pnl": 1.14,
      "mode": "paper",
      "running_pnl": 29.46
    },
    {
      "market": 88,
      "time": "2026-03-30 07:15:00 UTC",
      "phases": "Phase 1 + Phase 2 + Phase 3",
      "outcome": "P1: no trigger | P2: round trip complete | P3: snipe win @ $0.8750",
      "pnl": 0.53,
      "mode": "paper",
      "running_pnl": 28.33
    },
    {
      "market": 87,
      "time": "2026-03-30 07:10:00 UTC",
      "phases": "Phase 1 + Phase 2 + Phase 3",
      "outcome": "P1: directional win @ $0.9900 | P2: skipped \u2014 UP mid 0.5450 out of range | P3: snipe win @ $0.9200",
      "pnl": 6.01,
      "mode": "paper",
      "running_pnl": 27.8
    },
    {
      "market": 86,
      "time": "2026-03-30 07:05:00 UTC",
      "phases": "Phase 1 + Phase 2 + Phase 3",
      "outcome": "P1: directional win @ $0.9900 | P2: skipped \u2014 UP mid 0.5800 out of range | P3: snipe win @ $0.9900",
      "pnl": 4.05,
      "mode": "paper",
      "running_pnl": 21.79
    },
    {
      "market": 85,
      "time": "2026-03-30 07:00:00 UTC",
      "phases": "Phase 1 + Phase 2 + Phase 3",
      "outcome": "P1: no trigger | P2: buy(s) filled \u2014 exited at cutoff | P3: snipe loss @ $0.4300",
      "pnl": -4.42,
      "mode": "paper",
      "running_pnl": 17.73
    },
    {
      "market": 84,
      "time": "2026-03-30 06:55:00 UTC",
      "phases": "Phase 1 + Phase 2 + Phase 3",
      "outcome": "P1: no trigger | P2: round trip complete | P3: snipe win @ $0.9900",
      "pnl": 1.17,
      "mode": "paper",
      "running_pnl": 22.16
    },
    {
      "market": 83,
      "time": "2026-03-30 06:50:00 UTC",
      "phases": "Phase 1 + Phase 2 + Phase 3",
      "outcome": "P1: no trigger | P2: skipped \u2014 UP mid 0.5550 out of range | P3: snipe win @ $0.9900",
      "pnl": 0.48,
      "mode": "paper",
      "running_pnl": 20.99
    },
    {
      "market": 82,
      "time": "2026-03-30 06:45:00 UTC",
      "phases": "Phase 1 + Phase 2 + Phase 3",
      "outcome": "P1: directional win @ $0.9900 | P2: skipped \u2014 UP mid 0.6300 out of range | P3: snipe win @ $0.6500",
      "pnl": 1.49,
      "mode": "paper",
      "running_pnl": 20.51
    },
    {
      "market": 81,
      "time": "2026-03-30 06:40:00 UTC",
      "phases": "Phase 1 + Phase 2 + Phase 3",
      "outcome": "P1: no trigger | P2: buy(s) filled \u2014 stop loss exit | P3: snipe win @ $0.9900",
      "pnl": -1.97,
      "mode": "paper",
      "running_pnl": 19.02
    },
    {
      "market": 80,
      "time": "2026-03-30 06:35:00 UTC",
      "phases": "Phase 1 + Phase 2 + Phase 3",
      "outcome": "P1: no trigger | P2: skipped \u2014 UP mid 0.5550 out of range | P3: snipe loss @ $0.1150",
      "pnl": -4.35,
      "mode": "paper",
      "running_pnl": 20.99
    },
    {
      "market": 79,
      "time": "2026-03-30 06:30:00 UTC",
      "phases": "Phase 1 + Phase 2 + Phase 3",
      "outcome": "P1: no trigger | P2: round trip complete | P3: no snipe opportunity",
      "pnl": 0.66,
      "mode": "paper",
      "running_pnl": 25.34
    },
    {
      "market": 78,
      "time": "2026-03-30 06:25:00 UTC",
      "phases": "Phase 1 + Phase 2 + Phase 3",
      "outcome": "P1: no trigger | P2: skipped \u2014 UP mid 0.4450 out of range | P3: no snipe opportunity",
      "pnl": 0.0,
      "mode": "paper",
      "running_pnl": 24.68
    },
    {
      "market": 77,
      "time": "2026-03-30 06:20:00 UTC",
      "phases": "Phase 1 + Phase 2 + Phase 3",
      "outcome": "P1: directional win @ $0.9900 | P2: skipped \u2014 UP mid 0.3350 out of range | P3: snipe win @ $0.9150",
      "pnl": 2.55,
      "mode": "paper",
      "running_pnl": 24.68
    },
    {
      "market": 76,
      "time": "2026-03-30 06:15:00 UTC",
      "phases": "Phase 1 + Phase 2 + Phase 3",
      "outcome": "P1: directional win @ $0.9900 | P2: skipped \u2014 UP mid 0.4050 out of range | P3: snipe win @ $0.9900",
      "pnl": 3.84,
      "mode": "paper",
      "running_pnl": 22.13
    },
    {
      "market": 75,
      "time": "2026-03-30 06:10:00 UTC",
      "phases": "Phase 1 + Phase 2 + Phase 3",
      "outcome": "P1: directional win @ $0.9900 | P2: skipped \u2014 UP mid 0.4200 out of range | P3: snipe win @ $0.9900",
      "pnl": 4.02,
      "mode": "paper",
      "running_pnl": 18.29
    },
    {
      "market": 74,
      "time": "2026-03-30 06:05:00 UTC",
      "phases": "Phase 1 + Phase 2 + Phase 3",
      "outcome": "P1: no trigger | P2: buy(s) filled \u2014 stop loss exit | P3: snipe win @ $0.9900",
      "pnl": -1.51,
      "mode": "paper",
      "running_pnl": 14.27
    },
    {
      "market": 73,
      "time": "2026-03-30 06:00:00 UTC",
      "phases": "Phase 1 + Phase 2 + Phase 3",
      "outcome": "P1: directional loss @ $0.0100 | P2: skipped \u2014 UP mid 0.3800 out of range | P3: snipe win @ $0.9900",
      "pnl": -4.43,
      "mode": "paper",
      "running_pnl": 15.78
    },
    {
      "market": 72,
      "time": "2026-03-30 05:55:00 UTC",
      "phases": "Phase 1 + Phase 2 + Phase 3",
      "outcome": "P1: no trigger | P2: buy(s) filled \u2014 stop loss exit | P3: snipe win @ $0.9900",
      "pnl": -1.54,
      "mode": "paper",
      "running_pnl": 20.21
    },
    {
      "market": 71,
      "time": "2026-03-30 05:50:00 UTC",
      "phases": "Phase 1 + Phase 2 + Phase 3",
      "outcome": "P1: no trigger | P2: round trip complete | P3: snipe win @ $0.9900",
      "pnl": 0.96,
      "mode": "paper",
      "running_pnl": 21.75
    },
    {
      "market": 70,
      "time": "2026-03-30 05:45:00 UTC",
      "phases": "Phase 1 + Phase 2 + Phase 3",
      "outcome": "P1: no trigger | P2: round trip complete | P3: snipe win @ $0.9450",
      "pnl": 0.72,
      "mode": "paper",
      "running_pnl": 20.79
    },
    {
      "market": 69,
      "time": "2026-03-30 05:40:00 UTC",
      "phases": "Phase 1 + Phase 2 + Phase 3",
      "outcome": "P1: directional loss @ $0.0100 | P2: skipped \u2014 UP mid 0.4550 out of range | P3: snipe win @ $0.9900",
      "pnl": -4.4,
      "mode": "paper",
      "running_pnl": 20.07
    },
    {
      "market": 68,
      "time": "2026-03-30 05:35:00 UTC",
      "phases": "Phase 1 + Phase 2 + Phase 3",
      "outcome": "P1: no trigger | P2: round trip complete | P3: snipe win @ $0.9900",
      "pnl": 1.14,
      "mode": "paper",
      "running_pnl": 24.47
    },
    {
      "market": 67,
      "time": "2026-03-30 05:30:00 UTC",
      "phases": "Phase 1 + Phase 2 + Phase 3",
      "outcome": "P1: no trigger | P2: round trip complete | P3: snipe win @ $0.9900",
      "pnl": 1.11,
      "mode": "paper",
      "running_pnl": 23.33
    },
    {
      "market": 66,
      "time": "2026-03-30 05:25:00 UTC",
      "phases": "Phase 1 + Phase 2 + Phase 3",
      "outcome": "P1: no trigger | P2: round trip complete | P3: snipe win @ $0.9900",
      "pnl": 1.17,
      "mode": "paper",
      "running_pnl": 22.22
    },
    {
      "market": 65,
      "time": "2026-03-30 05:20:00 UTC",
      "phases": "Phase 1 + Phase 2 + Phase 3",
      "outcome": "P1: no trigger | P2: round trip complete | P3: no snipe opportunity",
      "pnl": 0.66,
      "mode": "paper",
      "running_pnl": 21.05
    },
    {
      "market": 64,
      "time": "2026-03-30 05:15:00 UTC",
      "phases": "Phase 1 + Phase 2 + Phase 3",
      "outcome": "P1: no trigger | P2: round trip complete | P3: snipe win @ $0.9450",
      "pnl": 0.89,
      "mode": "paper",
      "running_pnl": 20.4
    },
    {
      "market": 63,
      "time": "2026-03-30 05:10:00 UTC",
      "phases": "Phase 1 + Phase 2 + Phase 3",
      "outcome": "P1: directional win @ $0.9900 | P2: skipped \u2014 UP mid 0.3050 out of range | P3: snipe win @ $0.9900",
      "pnl": 2.64,
      "mode": "paper",
      "running_pnl": 19.51
    },
    {
      "market": 62,
      "time": "2026-03-30 05:05:00 UTC",
      "phases": "Phase 1 + Phase 2 + Phase 3",
      "outcome": "P1: no trigger | P2: round trip complete | P3: snipe win @ $0.9900",
      "pnl": 1.17,
      "mode": "paper",
      "running_pnl": 16.86
    },
    {
      "market": 61,
      "time": "2026-03-30 05:00:00 UTC",
      "phases": "Phase 1 + Phase 2 + Phase 3",
      "outcome": "P1: no trigger | P2: round trip complete | P3: snipe win @ $0.9900",
      "pnl": 1.14,
      "mode": "paper",
      "running_pnl": 15.7
    },
    {
      "market": 60,
      "time": "2026-03-30 04:55:00 UTC",
      "phases": "Phase 1 + Phase 2 + Phase 3",
      "outcome": "P1: no trigger | P2: round trip complete | P3: snipe win @ $0.9350",
      "pnl": 0.83,
      "mode": "paper",
      "running_pnl": 14.56
    },
    {
      "market": 59,
      "time": "2026-03-30 04:50:00 UTC",
      "phases": "Phase 1 + Phase 2 + Phase 3",
      "outcome": "P1: directional win @ $0.9900 | P2: skipped \u2014 UP mid 0.4550 out of range | P3: snipe win @ $0.9900",
      "pnl": 6.4,
      "mode": "paper",
      "running_pnl": 13.72
    },
    {
      "market": 58,
      "time": "2026-03-30 04:45:00 UTC",
      "phases": "Phase 1 + Phase 2 + Phase 3",
      "outcome": "P1: directional win @ $0.9900 | P2: skipped \u2014 UP mid 0.4550 out of range | P3: snipe win @ $0.9900",
      "pnl": 6.4,
      "mode": "paper",
      "running_pnl": 7.32
    },
    {
      "market": 57,
      "time": "2026-03-30 04:40:00 UTC",
      "phases": "Phase 1 + Phase 2 + Phase 3",
      "outcome": "P1: no trigger | P2: skipped \u2014 UP mid 0.4450 out of range | P3: snipe win @ $0.9900",
      "pnl": 0.51,
      "mode": "paper",
      "running_pnl": 0.93
    },
    {
      "market": 56,
      "time": "2026-03-30 04:35:00 UTC",
      "phases": "Phase 1 + Phase 2 + Phase 3",
      "outcome": "P1: no trigger | P2: buy(s) filled \u2014 stop loss exit | P3: snipe win @ $0.9900",
      "pnl": -1.54,
      "mode": "paper",
      "running_pnl": 0.42
    },
    {
      "market": 55,
      "time": "2026-03-30 04:30:00 UTC",
      "phases": "Phase 1 + Phase 2 + Phase 3",
      "outcome": "P1: directional win @ $0.9900 | P2: skipped \u2014 UP mid 0.6250 out of range | P3: snipe win @ $0.9900",
      "pnl": 3.41,
      "mode": "paper",
      "running_pnl": 1.96
    },
    {
      "market": 54,
      "time": "2026-03-30 04:25:00 UTC",
      "phases": "Phase 1 + Phase 2 + Phase 3",
      "outcome": "P1: no trigger | P2: round trip complete | P3: snipe win @ $0.9000",
      "pnl": 0.67,
      "mode": "paper",
      "running_pnl": -1.45
    },
    {
      "market": 53,
      "time": "2026-03-30 04:20:00 UTC",
      "phases": "Phase 1 + Phase 2 + Phase 3",
      "outcome": "P1: no trigger | P2: skipped \u2014 UP mid 0.4450 out of range | P3: no snipe opportunity",
      "pnl": 0.0,
      "mode": "paper",
      "running_pnl": -2.12
    },
    {
      "market": 52,
      "time": "2026-03-30 04:15:00 UTC",
      "phases": "Phase 1 + Phase 2 + Phase 3",
      "outcome": "P1: no trigger | P2: skipped \u2014 UP mid 0.4350 out of range | P3: snipe win @ $0.9900",
      "pnl": 0.42,
      "mode": "paper",
      "running_pnl": -2.12
    },
    {
      "market": 51,
      "time": "2026-03-30 04:10:00 UTC",
      "phases": "Phase 1 + Phase 2 + Phase 3",
      "outcome": "P1: no trigger | P2: round trip complete | P3: snipe win @ $0.9250",
      "pnl": 0.78,
      "mode": "paper",
      "running_pnl": -2.54
    },
    {
      "market": 50,
      "time": "2026-03-30 04:05:00 UTC",
      "phases": "Phase 1 + Phase 2 + Phase 3",
      "outcome": "P1: no trigger | P2: buy(s) filled \u2014 stop loss exit | P3: snipe win @ $0.9900",
      "pnl": -3.32,
      "mode": "paper",
      "running_pnl": -3.32
    }
  ]
}